{"iso3":"MAR","iso2":"MA","name":"Morocco","series":[{"year":1985,"generation":7.345,"demand":null,"demandPerCapita":null,"carbonIntensity":null,"netImports":null,"netImportsShare":null,"population":22113953,"coal":null,"gas":null,"oil":null,"nuclear":0,"hydro":0.486,"wind":0,"solar":0,"biofuel":null,"otherRenewables":null,"shares":{"coal":null,"gas":null,"oil":null,"nuclear":0,"hydro":6.62,"wind":0,"solar":0,"biofuel":null,"otherRenewables":null,"lowCarbon":6.62,"renewables":6.62,"fossil":null},"selfSufficiency":0.143,"fuelTrade":{"coalProduction":6.4,"coalConsumption":7.7,"oilProduction":0.6,"oilConsumption":55.3,"gasProduction":0.9,"gasConsumption":0.9},"energyPerGdp":0.789},{"year":1986,"generation":7.764,"demand":null,"demandPerCapita":null,"carbonIntensity":null,"netImports":null,"netImportsShare":null,"population":22600803,"coal":null,"gas":null,"oil":null,"nuclear":0,"hydro":0.643,"wind":0,"solar":0,"biofuel":null,"otherRenewables":null,"shares":{"coal":null,"gas":null,"oil":null,"nuclear":0,"hydro":8.28,"wind":0,"solar":0,"biofuel":null,"otherRenewables":null,"lowCarbon":8.28,"renewables":8.28,"fossil":null},"selfSufficiency":0.14,"fuelTrade":{"coalProduction":6.4,"coalConsumption":10.5,"oilProduction":0.3,"oilConsumption":54.3,"gasProduction":0.9,"gasConsumption":0.9},"energyPerGdp":0.756},{"year":1987,"generation":8.001,"demand":null,"demandPerCapita":null,"carbonIntensity":null,"netImports":null,"netImportsShare":null,"population":23054390,"coal":null,"gas":null,"oil":null,"nuclear":0,"hydro":0.825,"wind":0,"solar":0,"biofuel":null,"otherRenewables":null,"shares":{"coal":null,"gas":null,"oil":null,"nuclear":0,"hydro":10.31,"wind":0,"solar":0,"biofuel":null,"otherRenewables":null,"lowCarbon":10.31,"renewables":10.31,"fossil":null},"selfSufficiency":0.121,"fuelTrade":{"coalProduction":5.3,"coalConsumption":12.1,"oilProduction":0.2,"oilConsumption":54.3,"gasProduction":0.6,"gasConsumption":0.7},"energyPerGdp":0.797},{"year":1988,"generation":8.984,"demand":null,"demandPerCapita":null,"carbonIntensity":null,"netImports":null,"netImportsShare":null,"population":23500528,"coal":null,"gas":null,"oil":null,"nuclear":0,"hydro":0.936,"wind":0,"solar":0,"biofuel":null,"otherRenewables":null,"shares":{"coal":null,"gas":null,"oil":null,"nuclear":0,"hydro":10.42,"wind":0,"solar":0,"biofuel":null,"otherRenewables":null,"lowCarbon":10.42,"renewables":10.42,"fossil":null},"selfSufficiency":0.119,"fuelTrade":{"coalProduction":5.3,"coalConsumption":12,"oilProduction":0.2,"oilConsumption":58,"gasProduction":0.6,"gasConsumption":0.7},"energyPerGdp":0.764},{"year":1989,"generation":9.024,"demand":null,"demandPerCapita":null,"carbonIntensity":null,"netImports":null,"netImportsShare":null,"population":23939414,"coal":null,"gas":null,"oil":null,"nuclear":0,"hydro":1.157,"wind":0,"solar":0,"biofuel":null,"otherRenewables":null,"shares":{"coal":null,"gas":null,"oil":null,"nuclear":0,"hydro":12.82,"wind":0,"solar":0,"biofuel":null,"otherRenewables":null,"lowCarbon":12.82,"renewables":12.82,"fossil":null},"selfSufficiency":0.102,"fuelTrade":{"coalProduction":4.2,"coalConsumption":13.2,"oilProduction":0.2,"oilConsumption":63.7,"gasProduction":0.6,"gasConsumption":0.5},"energyPerGdp":0.821},{"year":1990,"generation":9.628,"demand":null,"demandPerCapita":null,"carbonIntensity":null,"netImports":null,"netImportsShare":null,"population":24375558,"coal":null,"gas":null,"oil":null,"nuclear":0,"hydro":1.22,"wind":0,"solar":0,"biofuel":null,"otherRenewables":null,"shares":{"coal":null,"gas":null,"oil":null,"nuclear":0,"hydro":12.67,"wind":0,"solar":0,"biofuel":null,"otherRenewables":null,"lowCarbon":12.67,"renewables":12.67,"fossil":null},"selfSufficiency":0.103,"fuelTrade":{"coalProduction":4.4,"coalConsumption":12.7,"oilProduction":0.2,"oilConsumption":65.9,"gasProduction":0.6,"gasConsumption":0.5},"energyPerGdp":0.81},{"year":1991,"generation":9.205,"demand":null,"demandPerCapita":null,"carbonIntensity":null,"netImports":null,"netImportsShare":null,"population":24799016,"coal":null,"gas":null,"oil":null,"nuclear":0,"hydro":1.226,"wind":0,"solar":0,"biofuel":null,"otherRenewables":null,"shares":{"coal":null,"gas":null,"oil":null,"nuclear":0,"hydro":13.32,"wind":0,"solar":0,"biofuel":null,"otherRenewables":null,"lowCarbon":13.32,"renewables":13.32,"fossil":null},"selfSufficiency":0.102,"fuelTrade":{"coalProduction":4.6,"coalConsumption":13.9,"oilProduction":0.2,"oilConsumption":66,"gasProduction":0.4,"gasConsumption":0.3},"energyPerGdp":0.764},{"year":1992,"generation":9.719,"demand":null,"demandPerCapita":null,"carbonIntensity":null,"netImports":null,"netImportsShare":null,"population":25212469,"coal":null,"gas":null,"oil":null,"nuclear":0,"hydro":0.964,"wind":0,"solar":0,"biofuel":null,"otherRenewables":null,"shares":{"coal":null,"gas":null,"oil":null,"nuclear":0,"hydro":9.92,"wind":0,"solar":0,"biofuel":null,"otherRenewables":null,"lowCarbon":9.92,"renewables":9.92,"fossil":null},"selfSufficiency":0.084,"fuelTrade":{"coalProduction":4.8,"coalConsumption":12.9,"oilProduction":0.1,"oilConsumption":77.8,"gasProduction":0.3,"gasConsumption":0.2},"energyPerGdp":0.871},{"year":1993,"generation":9.91,"demand":null,"demandPerCapita":null,"carbonIntensity":null,"netImports":null,"netImportsShare":null,"population":25614586,"coal":null,"gas":null,"oil":null,"nuclear":0,"hydro":0.443,"wind":0,"solar":0,"biofuel":null,"otherRenewables":null,"shares":{"coal":null,"gas":null,"oil":null,"nuclear":0,"hydro":4.47,"wind":0,"solar":0,"biofuel":null,"otherRenewables":null,"lowCarbon":4.47,"renewables":4.47,"fossil":null},"selfSufficiency":0.071,"fuelTrade":{"coalProduction":5,"coalConsumption":14.1,"oilProduction":0.1,"oilConsumption":79.2,"gasProduction":0.3,"gasConsumption":0.2},"energyPerGdp":0.885},{"year":1994,"generation":11.47,"demand":null,"demandPerCapita":null,"carbonIntensity":null,"netImports":null,"netImportsShare":null,"population":26000824,"coal":null,"gas":null,"oil":null,"nuclear":0,"hydro":0.84,"wind":0,"solar":0,"biofuel":null,"otherRenewables":null,"shares":{"coal":null,"gas":null,"oil":null,"nuclear":0,"hydro":7.32,"wind":0,"solar":0,"biofuel":null,"otherRenewables":null,"lowCarbon":7.32,"renewables":7.32,"fossil":null},"selfSufficiency":0.078,"fuelTrade":{"coalProduction":5.4,"coalConsumption":15.7,"oilProduction":0.1,"oilConsumption":86.1,"gasProduction":0.3,"gasConsumption":0.2},"energyPerGdp":0.88},{"year":1995,"generation":12.092,"demand":null,"demandPerCapita":null,"carbonIntensity":null,"netImports":null,"netImportsShare":null,"population":26399431,"coal":null,"gas":null,"oil":null,"nuclear":0,"hydro":0.611,"wind":0,"solar":0,"biofuel":null,"otherRenewables":null,"shares":{"coal":null,"gas":null,"oil":null,"nuclear":0,"hydro":5.05,"wind":0,"solar":0,"biofuel":null,"otherRenewables":null,"lowCarbon":5.05,"renewables":5.05,"fossil":null},"selfSufficiency":0.073,"fuelTrade":{"coalProduction":5.4,"coalConsumption":19,"oilProduction":0.2,"oilConsumption":81.5,"gasProduction":0.2,"gasConsumption":0.1},"energyPerGdp":0.912},{"year":1996,"generation":12.538,"demand":null,"demandPerCapita":null,"carbonIntensity":null,"netImports":null,"netImportsShare":null,"population":26808109,"coal":null,"gas":null,"oil":null,"nuclear":0,"hydro":1.957,"wind":0,"solar":0,"biofuel":null,"otherRenewables":null,"shares":{"coal":null,"gas":null,"oil":null,"nuclear":0,"hydro":15.61,"wind":0,"solar":0,"biofuel":null,"otherRenewables":null,"lowCarbon":15.61,"renewables":15.61,"fossil":null},"selfSufficiency":0.094,"fuelTrade":{"coalProduction":4.2,"coalConsumption":24.3,"oilProduction":0.2,"oilConsumption":76.9,"gasProduction":0.2,"gasConsumption":0.2},"energyPerGdp":0.85},{"year":1997,"generation":13.593,"demand":null,"demandPerCapita":null,"carbonIntensity":null,"netImports":null,"netImportsShare":null,"population":27213340,"coal":null,"gas":null,"oil":null,"nuclear":0,"hydro":2.083,"wind":0,"solar":0,"biofuel":null,"otherRenewables":null,"shares":{"coal":null,"gas":null,"oil":null,"nuclear":0,"hydro":15.32,"wind":0,"solar":0,"biofuel":null,"otherRenewables":null,"lowCarbon":15.32,"renewables":15.32,"fossil":null},"selfSufficiency":0.085,"fuelTrade":{"coalProduction":3.1,"coalConsumption":23.2,"oilProduction":0,"oilConsumption":81.7,"gasProduction":0.5,"gasConsumption":0.3},"energyPerGdp":0.899},{"year":1998,"generation":12.968,"demand":null,"demandPerCapita":null,"carbonIntensity":null,"netImports":null,"netImportsShare":null,"population":27621638,"coal":null,"gas":null,"oil":null,"nuclear":0,"hydro":1.777,"wind":0,"solar":0,"biofuel":null,"otherRenewables":null,"shares":{"coal":null,"gas":null,"oil":null,"nuclear":0,"hydro":13.7,"wind":0,"solar":0,"biofuel":null,"otherRenewables":null,"lowCarbon":13.7,"renewables":13.7,"fossil":null},"selfSufficiency":0.06,"fuelTrade":{"coalProduction":1.3,"coalConsumption":27.6,"oilProduction":0.1,"oilConsumption":81,"gasProduction":0.5,"gasConsumption":0.3},"energyPerGdp":0.861},{"year":1999,"generation":12.895,"demand":null,"demandPerCapita":null,"carbonIntensity":null,"netImports":null,"netImportsShare":null,"population":28027188,"coal":null,"gas":null,"oil":null,"nuclear":0,"hydro":0.825,"wind":0,"solar":0,"biofuel":null,"otherRenewables":null,"shares":{"coal":null,"gas":null,"oil":null,"nuclear":0,"hydro":6.4,"wind":0,"solar":0,"biofuel":null,"otherRenewables":null,"lowCarbon":6.4,"renewables":6.4,"fossil":null},"selfSufficiency":0.033,"fuelTrade":{"coalProduction":1.1,"coalConsumption":26.4,"oilProduction":0.1,"oilConsumption":89.3,"gasProduction":0.4,"gasConsumption":0.4},"energyPerGdp":0.884},{"year":2000,"generation":13.7,"demand":16.03,"demandPerCapita":564,"carbonIntensity":759.1,"netImports":2.33,"netImportsShare":14.54,"population":28423439,"coal":9.4,"gas":0,"oil":3.53,"nuclear":0,"hydro":0.71,"wind":0.06,"solar":0,"biofuel":0,"otherRenewables":0,"shares":{"coal":68.61,"gas":0,"oil":25.77,"nuclear":0,"hydro":5.18,"wind":0.44,"solar":0,"biofuel":0,"otherRenewables":0,"lowCarbon":5.62,"renewables":5.62,"fossil":94.38},"selfSufficiency":0.027,"fuelTrade":{"coalProduction":0.3,"coalConsumption":31.2,"oilProduction":0.2,"oilConsumption":83.5,"gasProduction":0.5,"gasConsumption":0.4},"energyPerGdp":0.86},{"year":2001,"generation":15.6,"demand":17.14,"demandPerCapita":595,"carbonIntensity":769.2,"netImports":1.54,"netImportsShare":8.98,"population":28814646,"coal":12.11,"gas":0,"oil":2.42,"nuclear":0,"hydro":0.86,"wind":0.21,"solar":0,"biofuel":0,"otherRenewables":0,"shares":{"coal":77.63,"gas":0,"oil":15.51,"nuclear":0,"hydro":5.51,"wind":1.35,"solar":0,"biofuel":0,"otherRenewables":0,"lowCarbon":6.86,"renewables":6.86,"fossil":93.14},"selfSufficiency":0.03,"fuelTrade":{"coalProduction":0,"coalConsumption":39.7,"oilProduction":0.2,"oilConsumption":83.6,"gasProduction":0.5,"gasConsumption":0.4},"energyPerGdp":0.865},{"year":2002,"generation":15.1,"demand":16.47,"demandPerCapita":564,"carbonIntensity":765.6,"netImports":1.37,"netImportsShare":8.32,"population":29198146,"coal":11.42,"gas":0,"oil":2.65,"nuclear":0,"hydro":0.84,"wind":0.19,"solar":0,"biofuel":0,"otherRenewables":0,"shares":{"coal":75.63,"gas":0,"oil":17.55,"nuclear":0,"hydro":5.56,"wind":1.26,"solar":0,"biofuel":0,"otherRenewables":0,"lowCarbon":6.82,"renewables":6.82,"fossil":93.18},"selfSufficiency":0.027,"fuelTrade":{"coalProduction":0,"coalConsumption":39.5,"oilProduction":0.2,"oilConsumption":87,"gasProduction":0.5,"gasConsumption":0.6},"energyPerGdp":0.859},{"year":2003,"generation":16.34,"demand":17.76,"demandPerCapita":601,"carbonIntensity":735,"netImports":1.42,"netImportsShare":8,"population":29571415,"coal":11.58,"gas":0,"oil":3.12,"nuclear":0,"hydro":1.44,"wind":0.2,"solar":0,"biofuel":0,"otherRenewables":0,"shares":{"coal":70.87,"gas":0,"oil":19.09,"nuclear":0,"hydro":8.81,"wind":1.22,"solar":0,"biofuel":0,"otherRenewables":0,"lowCarbon":10.04,"renewables":10.04,"fossil":89.96},"selfSufficiency":0.039,"fuelTrade":{"coalProduction":0,"coalConsumption":38.1,"oilProduction":0.1,"oilConsumption":87.1,"gasProduction":0.5,"gasConsumption":0.5},"energyPerGdp":0.812},{"year":2004,"generation":17.47,"demand":19,"demandPerCapita":634,"carbonIntensity":732.7,"netImports":1.53,"netImportsShare":8.05,"population":29953021,"coal":12.35,"gas":0.12,"oil":3.21,"nuclear":0,"hydro":1.59,"wind":0.2,"solar":0,"biofuel":0,"otherRenewables":0,"shares":{"coal":70.69,"gas":0.69,"oil":18.37,"nuclear":0,"hydro":9.1,"wind":1.15,"solar":0,"biofuel":0,"otherRenewables":0,"lowCarbon":10.25,"renewables":10.25,"fossil":89.75},"selfSufficiency":0.038,"fuelTrade":{"coalProduction":0.2,"coalConsumption":42.1,"oilProduction":0.1,"oilConsumption":100.6,"gasProduction":0.4,"gasConsumption":0.7},"energyPerGdp":0.882},{"year":2005,"generation":19.26,"demand":20.07,"demandPerCapita":661,"carbonIntensity":717,"netImports":0.81,"netImportsShare":4.04,"population":30358145,"coal":12.39,"gas":1.95,"oil":3.28,"nuclear":0,"hydro":1.43,"wind":0.21,"solar":0,"biofuel":0,"otherRenewables":0,"shares":{"coal":64.33,"gas":10.13,"oil":17.03,"nuclear":0,"hydro":7.42,"wind":1.09,"solar":0,"biofuel":0,"otherRenewables":0,"lowCarbon":8.52,"renewables":8.52,"fossil":91.48},"selfSufficiency":0.024,"fuelTrade":{"coalProduction":0.1,"coalConsumption":44.1,"oilProduction":0.1,"oilConsumption":109.3,"gasProduction":0.5,"gasConsumption":4.5},"energyPerGdp":0.925},{"year":2006,"generation":19.87,"demand":21.9,"demandPerCapita":712,"carbonIntensity":708.6,"netImports":2.03,"netImportsShare":9.27,"population":30771179,"coal":12.49,"gas":2.43,"oil":3.17,"nuclear":0,"hydro":1.6,"wind":0.18,"solar":0,"biofuel":0,"otherRenewables":0,"shares":{"coal":62.86,"gas":12.23,"oil":15.95,"nuclear":0,"hydro":8.05,"wind":0.91,"solar":0,"biofuel":0,"otherRenewables":0,"lowCarbon":8.96,"renewables":8.96,"fossil":91.04},"selfSufficiency":0.024,"fuelTrade":{"coalProduction":0,"coalConsumption":44.9,"oilProduction":0.1,"oilConsumption":110.9,"gasProduction":0.7,"gasConsumption":5.6},"energyPerGdp":0.875},{"year":2007,"generation":19.69,"demand":23.2,"demandPerCapita":744,"carbonIntensity":707.5,"netImports":3.51,"netImportsShare":15.13,"population":31186468,"coal":12.04,"gas":2.73,"oil":3.31,"nuclear":0,"hydro":1.33,"wind":0.28,"solar":0,"biofuel":0,"otherRenewables":0,"shares":{"coal":61.15,"gas":13.87,"oil":16.81,"nuclear":0,"hydro":6.75,"wind":1.42,"solar":0,"biofuel":0,"otherRenewables":0,"lowCarbon":8.18,"renewables":8.18,"fossil":91.82},"selfSufficiency":0.024,"fuelTrade":{"coalProduction":0,"coalConsumption":37.6,"oilProduction":0.1,"oilConsumption":116,"gasProduction":0.7,"gasConsumption":6.3},"energyPerGdp":0.836},{"year":2008,"generation":20.35,"demand":24.61,"demandPerCapita":779,"carbonIntensity":695.8,"netImports":4.26,"netImportsShare":17.31,"population":31606769,"coal":11.27,"gas":2.77,"oil":4.64,"nuclear":0,"hydro":1.37,"wind":0.3,"solar":0,"biofuel":0,"otherRenewables":0,"shares":{"coal":55.38,"gas":13.61,"oil":22.8,"nuclear":0,"hydro":6.73,"wind":1.47,"solar":0,"biofuel":0,"otherRenewables":0,"lowCarbon":8.21,"renewables":8.21,"fossil":91.79},"selfSufficiency":0.022,"fuelTrade":{"coalProduction":0,"coalConsumption":42.6,"oilProduction":0.1,"oilConsumption":127.9,"gasProduction":0.7,"gasConsumption":6.2},"energyPerGdp":0.869},{"year":2009,"generation":20.93,"demand":25.55,"demandPerCapita":798,"carbonIntensity":635.5,"netImports":4.62,"netImportsShare":18.08,"population":32030779,"coal":10.51,"gas":2.95,"oil":4.13,"nuclear":0,"hydro":2.95,"wind":0.39,"solar":0,"biofuel":0,"otherRenewables":0,"shares":{"coal":50.22,"gas":14.1,"oil":19.73,"nuclear":0,"hydro":14.1,"wind":1.86,"solar":0,"biofuel":0,"otherRenewables":0,"lowCarbon":15.96,"renewables":15.96,"fossil":84.04},"selfSufficiency":0.049,"fuelTrade":{"coalProduction":0,"coalConsumption":31.5,"oilProduction":0.1,"oilConsumption":129.2,"gasProduction":0.7,"gasConsumption":6.8},"energyPerGdp":0.811},{"year":2010,"generation":22.85,"demand":26.79,"demandPerCapita":825,"carbonIntensity":610.5,"netImports":3.94,"netImportsShare":14.71,"population":32467009,"coal":10.32,"gas":2.81,"oil":5.43,"nuclear":0,"hydro":3.63,"wind":0.66,"solar":0,"biofuel":0,"otherRenewables":0,"shares":{"coal":45.16,"gas":12.3,"oil":23.76,"nuclear":0,"hydro":15.89,"wind":2.89,"solar":0,"biofuel":0,"otherRenewables":0,"lowCarbon":18.77,"renewables":18.77,"fossil":81.22},"selfSufficiency":0.06,"fuelTrade":{"coalProduction":0,"coalConsumption":32.4,"oilProduction":0.1,"oilConsumption":143.7,"gasProduction":0.8,"gasConsumption":7.4},"energyPerGdp":0.864},{"year":2011,"generation":24.36,"demand":28.97,"demandPerCapita":880,"carbonIntensity":652.7,"netImports":4.61,"netImportsShare":15.91,"population":32912585,"coal":11.27,"gas":3.91,"oil":6.35,"nuclear":0,"hydro":2.14,"wind":0.69,"solar":0,"biofuel":0,"otherRenewables":0,"shares":{"coal":46.26,"gas":16.05,"oil":26.07,"nuclear":0,"hydro":8.79,"wind":2.83,"solar":0,"biofuel":0,"otherRenewables":0,"lowCarbon":11.62,"renewables":11.62,"fossil":88.38},"selfSufficiency":0.038,"fuelTrade":{"coalProduction":0,"coalConsumption":34.6,"oilProduction":0.1,"oilConsumption":153.3,"gasProduction":0.6,"gasConsumption":9.3},"energyPerGdp":0.86},{"year":2012,"generation":26.51,"demand":31.35,"demandPerCapita":940,"carbonIntensity":648.4,"netImports":4.84,"netImportsShare":15.44,"population":33355246,"coal":11.37,"gas":5.95,"oil":6.64,"nuclear":0,"hydro":1.82,"wind":0.73,"solar":0,"biofuel":0,"otherRenewables":0,"shares":{"coal":42.89,"gas":22.44,"oil":25.05,"nuclear":0,"hydro":6.87,"wind":2.75,"solar":0,"biofuel":0,"otherRenewables":0,"lowCarbon":9.62,"renewables":9.62,"fossil":90.38},"selfSufficiency":0.034,"fuelTrade":{"coalProduction":0,"coalConsumption":35.2,"oilProduction":0.1,"oilConsumption":154.3,"gasProduction":0.8,"gasConsumption":12.5},"energyPerGdp":0.85},{"year":2013,"generation":26.94,"demand":32.34,"demandPerCapita":957,"carbonIntensity":612.5,"netImports":5.4,"netImportsShare":16.7,"population":33787573,"coal":12.14,"gas":5.82,"oil":4.63,"nuclear":0,"hydro":2.99,"wind":1.36,"solar":0,"biofuel":0,"otherRenewables":0,"shares":{"coal":45.06,"gas":21.6,"oil":17.19,"nuclear":0,"hydro":11.1,"wind":5.05,"solar":0,"biofuel":0,"otherRenewables":0,"lowCarbon":16.15,"renewables":16.15,"fossil":83.85},"selfSufficiency":0.053,"fuelTrade":{"coalProduction":0,"coalConsumption":34.9,"oilProduction":0.1,"oilConsumption":156.1,"gasProduction":1,"gasConsumption":12.1},"energyPerGdp":0.835},{"year":2014,"generation":28.08,"demand":34.09,"demandPerCapita":997,"carbonIntensity":651.4,"netImports":6.01,"netImportsShare":17.63,"population":34204784,"coal":15.95,"gas":5.6,"oil":2.57,"nuclear":0,"hydro":2.03,"wind":1.92,"solar":0,"biofuel":0.01,"otherRenewables":0,"shares":{"coal":56.8,"gas":19.94,"oil":9.15,"nuclear":0,"hydro":7.23,"wind":6.84,"solar":0,"biofuel":0.04,"otherRenewables":0,"lowCarbon":14.1,"renewables":14.1,"fossil":85.9},"selfSufficiency":0.047,"fuelTrade":{"coalProduction":0,"coalConsumption":47,"oilProduction":0.1,"oilConsumption":148.7,"gasProduction":1,"gasConsumption":11.7},"energyPerGdp":0.824},{"year":2015,"generation":29.91,"demand":34.88,"demandPerCapita":1008,"carbonIntensity":639.9,"netImports":4.97,"netImportsShare":14.25,"population":34607590,"coal":17.11,"gas":5.78,"oil":2.21,"nuclear":0,"hydro":2.28,"wind":2.52,"solar":0,"biofuel":0.01,"otherRenewables":0,"shares":{"coal":57.2,"gas":19.32,"oil":7.39,"nuclear":0,"hydro":7.62,"wind":8.43,"solar":0,"biofuel":0.03,"otherRenewables":0,"lowCarbon":16.08,"renewables":16.08,"fossil":83.92},"selfSufficiency":0.056,"fuelTrade":{"coalProduction":0,"coalConsumption":51.7,"oilProduction":0.1,"oilConsumption":145.5,"gasProduction":1,"gasConsumption":11.8},"energyPerGdp":0.804},{"year":2016,"generation":30.87,"demand":36.02,"demandPerCapita":1028,"carbonIntensity":633.6,"netImports":5.15,"netImportsShare":14.3,"population":35023459,"coal":16.99,"gas":5.91,"oil":2.88,"nuclear":0,"hydro":1.66,"wind":3.02,"solar":0.4,"biofuel":0.01,"otherRenewables":0,"shares":{"coal":55.04,"gas":19.14,"oil":9.33,"nuclear":0,"hydro":5.38,"wind":9.78,"solar":1.3,"biofuel":0.03,"otherRenewables":0,"lowCarbon":16.49,"renewables":16.49,"fossil":83.51},"selfSufficiency":0.057,"fuelTrade":{"coalProduction":0,"coalConsumption":49.8,"oilProduction":0.1,"oilConsumption":149.1,"gasProduction":0.9,"gasConsumption":12},"energyPerGdp":0.809},{"year":2017,"generation":31.94,"demand":37.84,"demandPerCapita":1068,"carbonIntensity":637.5,"netImports":5.9,"netImportsShare":15.59,"population":35446395,"coal":17.55,"gas":5.84,"oil":3.49,"nuclear":0,"hydro":1.57,"wind":3.04,"solar":0.41,"biofuel":0.04,"otherRenewables":0,"shares":{"coal":54.95,"gas":18.28,"oil":10.93,"nuclear":0,"hydro":4.92,"wind":9.52,"solar":1.28,"biofuel":0.13,"otherRenewables":0,"lowCarbon":15.84,"renewables":15.84,"fossil":84.16},"selfSufficiency":null,"fuelTrade":{"coalProduction":null,"coalConsumption":51.8,"oilProduction":null,"oilConsumption":157.8,"gasProduction":null,"gasConsumption":11.9},"energyPerGdp":0.806},{"year":2018,"generation":34.56,"demand":37.93,"demandPerCapita":1058,"carbonIntensity":621.5,"netImports":3.37,"netImportsShare":8.88,"population":35839760,"coal":21.26,"gas":5.2,"oil":1.25,"nuclear":0,"hydro":2,"wind":3.86,"solar":0.95,"biofuel":0.04,"otherRenewables":0,"shares":{"coal":61.52,"gas":15.05,"oil":3.62,"nuclear":0,"hydro":5.79,"wind":11.17,"solar":2.75,"biofuel":0.12,"otherRenewables":0,"lowCarbon":19.82,"renewables":19.82,"fossil":80.18},"selfSufficiency":null,"fuelTrade":{"coalProduction":null,"coalConsumption":59.9,"oilProduction":null,"oilConsumption":154.1,"gasProduction":null,"gasConsumption":10.7},"energyPerGdp":0.809},{"year":2019,"generation":40.38,"demand":39.45,"demandPerCapita":1089,"carbonIntensity":631.8,"netImports":-0.93,"netImportsShare":-2.36,"population":36210907,"coal":26.9,"gas":4.7,"oil":0.79,"nuclear":0,"hydro":1.65,"wind":4.72,"solar":1.58,"biofuel":0.04,"otherRenewables":0,"shares":{"coal":66.62,"gas":11.64,"oil":1.96,"nuclear":0,"hydro":4.09,"wind":11.69,"solar":3.91,"biofuel":0.1,"otherRenewables":0,"lowCarbon":19.79,"renewables":19.79,"fossil":80.21},"selfSufficiency":null,"fuelTrade":{"coalProduction":null,"coalConsumption":77.5,"oilProduction":null,"oilConsumption":156.3,"gasProduction":null,"gasConsumption":10.1},"energyPerGdp":0.858},{"year":2020,"generation":38.8,"demand":39.03,"demandPerCapita":1067,"carbonIntensity":645.6,"netImports":0.23,"netImportsShare":0.59,"population":36584208,"coal":27.21,"gas":3.46,"oil":0.69,"nuclear":0,"hydro":1.29,"wind":4.59,"solar":1.52,"biofuel":0.04,"otherRenewables":0,"shares":{"coal":70.13,"gas":8.92,"oil":1.78,"nuclear":0,"hydro":3.33,"wind":11.83,"solar":3.92,"biofuel":0.1,"otherRenewables":0,"lowCarbon":19.18,"renewables":19.18,"fossil":80.83},"selfSufficiency":null,"fuelTrade":{"coalProduction":null,"coalConsumption":79.8,"oilProduction":null,"oilConsumption":136.4,"gasProduction":null,"gasConsumption":7.9},"energyPerGdp":0.849},{"year":2021,"generation":41.3,"demand":41.14,"demandPerCapita":1113,"carbonIntensity":640,"netImports":-0.16,"netImportsShare":-0.39,"population":36954443,"coal":28.28,"gas":3.46,"oil":1.38,"nuclear":0,"hydro":1.21,"wind":5.11,"solar":1.82,"biofuel":0.04,"otherRenewables":0,"shares":{"coal":68.47,"gas":8.38,"oil":3.34,"nuclear":0,"hydro":2.93,"wind":12.37,"solar":4.41,"biofuel":0.1,"otherRenewables":0,"lowCarbon":19.81,"renewables":19.81,"fossil":80.19},"selfSufficiency":null,"fuelTrade":{"coalProduction":null,"coalConsumption":86,"oilProduction":null,"oilConsumption":154.7,"gasProduction":null,"gasConsumption":7.9},"energyPerGdp":0.873},{"year":2022,"generation":41.41,"demand":42.81,"demandPerCapita":1147,"carbonIntensity":662.6,"netImports":1.4,"netImportsShare":3.27,"population":37329068,"coal":29,"gas":0.69,"oil":4.19,"nuclear":0,"hydro":0.68,"wind":5.36,"solar":1.45,"biofuel":0.04,"otherRenewables":0,"shares":{"coal":70.03,"gas":1.67,"oil":10.12,"nuclear":0,"hydro":1.64,"wind":12.94,"solar":3.5,"biofuel":0.1,"otherRenewables":0,"lowCarbon":18.18,"renewables":18.18,"fossil":81.82},"selfSufficiency":null,"fuelTrade":{"coalProduction":null,"coalConsumption":86.4,"oilProduction":null,"oilConsumption":159.5,"gasProduction":null,"gasConsumption":2.2},"energyPerGdp":0.856},{"year":2023,"generation":42.46,"demand":44.31,"demandPerCapita":1175,"carbonIntensity":616.4,"netImports":1.85,"netImportsShare":4.17,"population":37712516,"coal":27.15,"gas":4.26,"oil":1.83,"nuclear":0,"hydro":0.52,"wind":6.55,"solar":2.11,"biofuel":0.04,"otherRenewables":0,"shares":{"coal":63.94,"gas":10.03,"oil":4.31,"nuclear":0,"hydro":1.23,"wind":15.43,"solar":4.97,"biofuel":0.09,"otherRenewables":0,"lowCarbon":21.71,"renewables":21.71,"fossil":78.28},"selfSufficiency":null,"fuelTrade":{"coalProduction":null,"coalConsumption":81,"oilProduction":null,"oilConsumption":158.3,"gasProduction":null,"gasConsumption":8.9},"energyPerGdp":null},{"year":2024,"generation":42.4,"demand":44.94,"demandPerCapita":1180,"carbonIntensity":594.8,"netImports":2.54,"netImportsShare":5.65,"population":38081176,"coal":26.18,"gas":4.33,"oil":1.54,"nuclear":0,"hydro":0.81,"wind":7.09,"solar":2.41,"biofuel":0.04,"otherRenewables":0,"shares":{"coal":61.74,"gas":10.21,"oil":3.63,"nuclear":0,"hydro":1.91,"wind":16.72,"solar":5.68,"biofuel":0.09,"otherRenewables":0,"lowCarbon":24.41,"renewables":24.41,"fossil":75.59},"selfSufficiency":null,"fuelTrade":{"coalProduction":null,"coalConsumption":73.7,"oilProduction":null,"oilConsumption":168.3,"gasProduction":null,"gasConsumption":9},"energyPerGdp":null,"splitEstimated":true},{"year":2025,"generation":44.5,"demand":48.23,"demandPerCapita":1255,"carbonIntensity":596.4,"netImports":3.73,"netImportsShare":7.73,"population":38430774,"coal":27.37,"gas":4.86,"oil":1.61,"nuclear":0,"hydro":0.91,"wind":7.14,"solar":2.57,"biofuel":0.04,"otherRenewables":0,"shares":{"coal":61.51,"gas":10.92,"oil":3.62,"nuclear":0,"hydro":2.04,"wind":16.05,"solar":5.78,"biofuel":0.09,"otherRenewables":0,"lowCarbon":23.95,"renewables":23.95,"fossil":76.05},"selfSufficiency":null,"fuelTrade":{"coalProduction":null,"coalConsumption":null,"oilProduction":null,"oilConsumption":null,"gasProduction":null,"gasConsumption":null},"energyPerGdp":null,"splitEstimated":true}]}