{"iso3":"MNG","iso2":"MN","name":"Mongolia","series":[{"year":2000,"generation":2.9,"demand":3.06,"demandPerCapita":1246,"carbonIntensity":910.4,"netImports":0.16,"netImportsShare":5.23,"population":2455182,"coal":2.85,"gas":0,"oil":0.05,"nuclear":0,"hydro":0,"wind":0,"solar":0,"biofuel":0,"otherRenewables":0,"shares":{"coal":98.28,"gas":0,"oil":1.72,"nuclear":0,"hydro":0,"wind":0,"solar":0,"biofuel":0,"otherRenewables":0,"lowCarbon":0,"renewables":0,"fossil":100},"selfSufficiency":1.621,"fuelTrade":{"coalProduction":27.4,"coalConsumption":null,"oilProduction":0.1,"oilConsumption":null,"gasProduction":0,"gasConsumption":null},"energyPerGdp":2.352},{"year":2001,"generation":2.97,"demand":3.15,"demandPerCapita":1271,"carbonIntensity":909.1,"netImports":0.18,"netImportsShare":5.71,"population":2477704,"coal":2.91,"gas":0,"oil":0.06,"nuclear":0,"hydro":0,"wind":0,"solar":0,"biofuel":0,"otherRenewables":0,"shares":{"coal":97.98,"gas":0,"oil":2.02,"nuclear":0,"hydro":0,"wind":0,"solar":0,"biofuel":0,"otherRenewables":0,"lowCarbon":0,"renewables":0,"fossil":100},"selfSufficiency":1.621,"fuelTrade":{"coalProduction":27.2,"coalConsumption":null,"oilProduction":0.1,"oilConsumption":null,"gasProduction":0,"gasConsumption":null},"energyPerGdp":2.162},{"year":2002,"generation":3.09,"demand":3.24,"demandPerCapita":1296,"carbonIntensity":909.4,"netImports":0.15,"netImportsShare":4.63,"population":2500074,"coal":3.02,"gas":0,"oil":0.07,"nuclear":0,"hydro":0,"wind":0,"solar":0,"biofuel":0,"otherRenewables":0,"shares":{"coal":97.73,"gas":0,"oil":2.27,"nuclear":0,"hydro":0,"wind":0,"solar":0,"biofuel":0,"otherRenewables":0,"lowCarbon":0,"renewables":0,"fossil":100},"selfSufficiency":1.646,"fuelTrade":{"coalProduction":29.3,"coalConsumption":null,"oilProduction":0.2,"oilConsumption":null,"gasProduction":0,"gasConsumption":null},"energyPerGdp":2.097},{"year":2003,"generation":3.11,"demand":3.27,"demandPerCapita":1297,"carbonIntensity":910,"netImports":0.16,"netImportsShare":4.89,"population":2521809,"coal":3.04,"gas":0,"oil":0.07,"nuclear":0,"hydro":0,"wind":0,"solar":0,"biofuel":0,"otherRenewables":0,"shares":{"coal":97.75,"gas":0,"oil":2.25,"nuclear":0,"hydro":0,"wind":0,"solar":0,"biofuel":0,"otherRenewables":0,"lowCarbon":0,"renewables":0,"fossil":100},"selfSufficiency":1.699,"fuelTrade":{"coalProduction":30,"coalConsumption":null,"oilProduction":0.3,"oilConsumption":null,"gasProduction":0,"gasConsumption":null},"energyPerGdp":1.854},{"year":2004,"generation":3.28,"demand":3.44,"demandPerCapita":1353,"carbonIntensity":908.5,"netImports":0.16,"netImportsShare":4.65,"population":2542801,"coal":3.19,"gas":0,"oil":0.09,"nuclear":0,"hydro":0,"wind":0,"solar":0,"biofuel":0,"otherRenewables":0,"shares":{"coal":97.26,"gas":0,"oil":2.74,"nuclear":0,"hydro":0,"wind":0,"solar":0,"biofuel":0,"otherRenewables":0,"lowCarbon":0,"renewables":0,"fossil":100},"selfSufficiency":1.863,"fuelTrade":{"coalProduction":36.3,"coalConsumption":null,"oilProduction":0.4,"oilConsumption":null,"gasProduction":0,"gasConsumption":null},"energyPerGdp":1.766},{"year":2005,"generation":3.4,"demand":3.56,"demandPerCapita":1389,"carbonIntensity":908.8,"netImports":0.16,"netImportsShare":4.49,"population":2563466,"coal":3.31,"gas":0,"oil":0.09,"nuclear":0,"hydro":0,"wind":0,"solar":0,"biofuel":0,"otherRenewables":0,"shares":{"coal":97.35,"gas":0,"oil":2.65,"nuclear":0,"hydro":0,"wind":0,"solar":0,"biofuel":0,"otherRenewables":0,"lowCarbon":0,"renewables":0,"fossil":100},"selfSufficiency":1.972,"fuelTrade":{"coalProduction":39.8,"coalConsumption":null,"oilProduction":0.4,"oilConsumption":null,"gasProduction":0,"gasConsumption":null},"energyPerGdp":1.622},{"year":2006,"generation":3.53,"demand":3.75,"demandPerCapita":1451,"carbonIntensity":909.4,"netImports":0.22,"netImportsShare":5.87,"population":2584761,"coal":3.43,"gas":0,"oil":0.1,"nuclear":0,"hydro":0,"wind":0,"solar":0,"biofuel":0,"otherRenewables":0,"shares":{"coal":97.17,"gas":0,"oil":2.83,"nuclear":0,"hydro":0,"wind":0,"solar":0,"biofuel":0,"otherRenewables":0,"lowCarbon":0,"renewables":0,"fossil":100},"selfSufficiency":2.02,"fuelTrade":{"coalProduction":42.7,"coalConsumption":null,"oilProduction":0.7,"oilConsumption":null,"gasProduction":0,"gasConsumption":null},"energyPerGdp":1.503},{"year":2007,"generation":3.71,"demand":3.91,"demandPerCapita":1499,"carbonIntensity":905.7,"netImports":0.2,"netImportsShare":5.12,"population":2607976,"coal":3.55,"gas":0,"oil":0.16,"nuclear":0,"hydro":0,"wind":0,"solar":0,"biofuel":0,"otherRenewables":0,"shares":{"coal":95.69,"gas":0,"oil":4.31,"nuclear":0,"hydro":0,"wind":0,"solar":0,"biofuel":0,"otherRenewables":0,"lowCarbon":0,"renewables":0,"fossil":100},"selfSufficiency":2.115,"fuelTrade":{"coalProduction":48.9,"coalConsumption":null,"oilProduction":1.5,"oilConsumption":null,"gasProduction":0,"gasConsumption":null},"energyPerGdp":1.442},{"year":2008,"generation":4,"demand":4.18,"demandPerCapita":1587,"carbonIntensity":905,"netImports":0.18,"netImportsShare":4.31,"population":2634431,"coal":3.83,"gas":0,"oil":0.16,"nuclear":0,"hydro":0,"wind":0,"solar":0.01,"biofuel":0,"otherRenewables":0,"shares":{"coal":95.75,"gas":0,"oil":4,"nuclear":0,"hydro":0,"wind":0,"solar":0.25,"biofuel":0,"otherRenewables":0,"lowCarbon":0.25,"renewables":0.25,"fossil":99.75},"selfSufficiency":2.204,"fuelTrade":{"coalProduction":53.3,"coalConsumption":null,"oilProduction":2.1,"oilConsumption":null,"gasProduction":0,"gasConsumption":null},"energyPerGdp":1.332},{"year":2009,"generation":4.04,"demand":4.18,"demandPerCapita":1568,"carbonIntensity":898.5,"netImports":0.14,"netImportsShare":3.35,"population":2665333,"coal":3.86,"gas":0,"oil":0.15,"nuclear":0,"hydro":0.02,"wind":0,"solar":0.01,"biofuel":0,"otherRenewables":0,"shares":{"coal":95.55,"gas":0,"oil":3.71,"nuclear":0,"hydro":0.49,"wind":0,"solar":0.25,"biofuel":0,"otherRenewables":0,"lowCarbon":0.74,"renewables":0.74,"fossil":99.26},"selfSufficiency":2.993,"fuelTrade":{"coalProduction":76.4,"coalConsumption":null,"oilProduction":3.3,"oilConsumption":null,"gasProduction":0,"gasConsumption":null},"energyPerGdp":1.363},{"year":2010,"generation":4.32,"demand":4.56,"demandPerCapita":1688,"carbonIntensity":893.5,"netImports":0.24,"netImportsShare":5.26,"population":2701739,"coal":4.09,"gas":0,"oil":0.18,"nuclear":0,"hydro":0.04,"wind":0,"solar":0.01,"biofuel":0,"otherRenewables":0,"shares":{"coal":94.68,"gas":0,"oil":4.17,"nuclear":0,"hydro":0.93,"wind":0,"solar":0.23,"biofuel":0,"otherRenewables":0,"lowCarbon":1.16,"renewables":1.16,"fossil":98.84},"selfSufficiency":4.141,"fuelTrade":{"coalProduction":133.1,"coalConsumption":null,"oilProduction":3.8,"oilConsumption":null,"gasProduction":0,"gasConsumption":null},"energyPerGdp":1.518},{"year":2011,"generation":4.54,"demand":4.79,"demandPerCapita":1745,"carbonIntensity":889.9,"netImports":0.25,"netImportsShare":5.22,"population":2745183,"coal":4.24,"gas":0,"oil":0.24,"nuclear":0,"hydro":0.05,"wind":0,"solar":0.01,"biofuel":0,"otherRenewables":0,"shares":{"coal":93.39,"gas":0,"oil":5.29,"nuclear":0,"hydro":1.1,"wind":0,"solar":0.22,"biofuel":0,"otherRenewables":0,"lowCarbon":1.32,"renewables":1.32,"fossil":98.68},"selfSufficiency":5,"fuelTrade":{"coalProduction":174.6,"coalConsumption":null,"oilProduction":4.5,"oilConsumption":null,"gasProduction":0,"gasConsumption":null},"energyPerGdp":1.312},{"year":2012,"generation":4.81,"demand":5.15,"demandPerCapita":1842,"carbonIntensity":889.8,"netImports":0.34,"netImportsShare":6.6,"population":2795463,"coal":4.5,"gas":0,"oil":0.25,"nuclear":0,"hydro":0.05,"wind":0,"solar":0.01,"biofuel":0,"otherRenewables":0,"shares":{"coal":93.56,"gas":0,"oil":5.2,"nuclear":0,"hydro":1.04,"wind":0,"solar":0.21,"biofuel":0,"otherRenewables":0,"lowCarbon":1.25,"renewables":1.25,"fossil":98.75},"selfSufficiency":4.094,"fuelTrade":{"coalProduction":164.8,"coalConsumption":null,"oilProduction":6.4,"oilConsumption":null,"gasProduction":0,"gasConsumption":null},"energyPerGdp":1.388},{"year":2013,"generation":5.02,"demand":6.2,"demandPerCapita":2174,"carbonIntensity":880.5,"netImports":1.18,"netImportsShare":19.03,"population":2851887,"coal":4.63,"gas":0,"oil":0.27,"nuclear":0,"hydro":0.06,"wind":0.05,"solar":0.01,"biofuel":0,"otherRenewables":0,"shares":{"coal":92.23,"gas":0,"oil":5.38,"nuclear":0,"hydro":1.2,"wind":1,"solar":0.2,"biofuel":0,"otherRenewables":0,"lowCarbon":2.39,"renewables":2.39,"fossil":97.61},"selfSufficiency":3.905,"fuelTrade":{"coalProduction":176.4,"coalConsumption":null,"oilProduction":9,"oilConsumption":null,"gasProduction":0,"gasConsumption":null},"energyPerGdp":1.413},{"year":2014,"generation":5.38,"demand":6.7,"demandPerCapita":2300,"carbonIntensity":868,"netImports":1.32,"netImportsShare":19.7,"population":2913041,"coal":4.93,"gas":0,"oil":0.24,"nuclear":0,"hydro":0.07,"wind":0.13,"solar":0.01,"biofuel":0,"otherRenewables":0,"shares":{"coal":91.64,"gas":0,"oil":4.46,"nuclear":0,"hydro":1.3,"wind":2.42,"solar":0.19,"biofuel":0,"otherRenewables":0,"lowCarbon":3.9,"renewables":3.9,"fossil":96.1},"selfSufficiency":2.908,"fuelTrade":{"coalProduction":129.4,"coalConsumption":null,"oilProduction":13.1,"oilConsumption":null,"gasProduction":0,"gasConsumption":null},"energyPerGdp":1.35},{"year":2015,"generation":5.51,"demand":6.88,"demandPerCapita":2311,"carbonIntensity":867.5,"netImports":1.37,"netImportsShare":19.91,"population":2976528,"coal":5.06,"gas":0,"oil":0.23,"nuclear":0,"hydro":0.06,"wind":0.15,"solar":0.01,"biofuel":0,"otherRenewables":0,"shares":{"coal":91.83,"gas":0,"oil":4.17,"nuclear":0,"hydro":1.09,"wind":2.72,"solar":0.18,"biofuel":0,"otherRenewables":0,"lowCarbon":3.99,"renewables":3.99,"fossil":96.01},"selfSufficiency":3.047,"fuelTrade":{"coalProduction":127.8,"coalConsumption":null,"oilProduction":14.9,"oilConsumption":null,"gasProduction":0,"gasConsumption":null},"energyPerGdp":1.262},{"year":2016,"generation":5.67,"demand":7.08,"demandPerCapita":2328,"carbonIntensity":867.7,"netImports":1.41,"netImportsShare":19.91,"population":3040815,"coal":5.23,"gas":0,"oil":0.19,"nuclear":0,"hydro":0.09,"wind":0.15,"solar":0.01,"biofuel":0,"otherRenewables":0,"shares":{"coal":92.24,"gas":0,"oil":3.35,"nuclear":0,"hydro":1.59,"wind":2.65,"solar":0.18,"biofuel":0,"otherRenewables":0,"lowCarbon":4.41,"renewables":4.41,"fossil":95.59},"selfSufficiency":4.243,"fuelTrade":{"coalProduction":185.7,"coalConsumption":null,"oilProduction":15.1,"oilConsumption":null,"gasProduction":0,"gasConsumption":null},"energyPerGdp":1.268},{"year":2017,"generation":6.03,"demand":7.58,"demandPerCapita":2442,"carbonIntensity":865.7,"netImports":1.55,"netImportsShare":20.45,"population":3104371,"coal":5.5,"gas":0,"oil":0.28,"nuclear":0,"hydro":0.08,"wind":0.14,"solar":0.03,"biofuel":0,"otherRenewables":0,"shares":{"coal":91.21,"gas":0,"oil":4.64,"nuclear":0,"hydro":1.33,"wind":2.32,"solar":0.5,"biofuel":0,"otherRenewables":0,"lowCarbon":4.15,"renewables":4.15,"fossil":95.85},"selfSufficiency":5,"fuelTrade":{"coalProduction":261.8,"coalConsumption":null,"oilProduction":null,"oilConsumption":null,"gasProduction":null,"gasConsumption":null},"energyPerGdp":1.332},{"year":2018,"generation":6.57,"demand":8.21,"demandPerCapita":2592,"carbonIntensity":843.2,"netImports":1.64,"netImportsShare":19.98,"population":3167714,"coal":5.83,"gas":0,"oil":0.3,"nuclear":0,"hydro":0.08,"wind":0.3,"solar":0.06,"biofuel":0,"otherRenewables":0,"shares":{"coal":88.74,"gas":0,"oil":4.57,"nuclear":0,"hydro":1.22,"wind":4.57,"solar":0.91,"biofuel":0,"otherRenewables":0,"lowCarbon":6.7,"renewables":6.7,"fossil":93.3},"selfSufficiency":5,"fuelTrade":{"coalProduction":288.8,"coalConsumption":null,"oilProduction":null,"oilConsumption":null,"gasProduction":null,"gasConsumption":null},"energyPerGdp":1.367},{"year":2019,"generation":6.94,"demand":8.64,"demandPerCapita":2673,"carbonIntensity":812.7,"netImports":1.7,"netImportsShare":19.68,"population":3232118,"coal":5.88,"gas":0,"oil":0.37,"nuclear":0,"hydro":0.09,"wind":0.48,"solar":0.12,"biofuel":0,"otherRenewables":0,"shares":{"coal":84.73,"gas":0,"oil":5.33,"nuclear":0,"hydro":1.3,"wind":6.92,"solar":1.73,"biofuel":0,"otherRenewables":0,"lowCarbon":9.94,"renewables":9.94,"fossil":90.06},"selfSufficiency":4.837,"fuelTrade":{"coalProduction":302.3,"coalConsumption":null,"oilProduction":null,"oilConsumption":null,"gasProduction":null,"gasConsumption":null},"energyPerGdp":1.421},{"year":2020,"generation":6.64,"demand":8.28,"demandPerCapita":2516,"carbonIntensity":810.2,"netImports":1.64,"netImportsShare":19.81,"population":3290786,"coal":5.61,"gas":0,"oil":0.35,"nuclear":0,"hydro":0.08,"wind":0.48,"solar":0.12,"biofuel":0,"otherRenewables":0,"shares":{"coal":84.49,"gas":0,"oil":5.27,"nuclear":0,"hydro":1.21,"wind":7.23,"solar":1.81,"biofuel":0,"otherRenewables":0,"lowCarbon":10.24,"renewables":10.24,"fossil":89.76},"selfSufficiency":3.647,"fuelTrade":{"coalProduction":228,"coalConsumption":null,"oilProduction":null,"oilConsumption":null,"gasProduction":null,"gasConsumption":null},"energyPerGdp":1.489},{"year":2021,"generation":7.44,"demand":9.24,"demandPerCapita":2767,"carbonIntensity":802.4,"netImports":1.8,"netImportsShare":19.48,"population":3339676,"coal":6.27,"gas":0,"oil":0.34,"nuclear":0,"hydro":0.08,"wind":0.58,"solar":0.17,"biofuel":0,"otherRenewables":0,"shares":{"coal":84.27,"gas":0,"oil":4.57,"nuclear":0,"hydro":1.07,"wind":7.8,"solar":2.29,"biofuel":0,"otherRenewables":0,"lowCarbon":11.16,"renewables":11.16,"fossil":88.84},"selfSufficiency":2.811,"fuelTrade":{"coalProduction":171,"coalConsumption":null,"oilProduction":null,"oilConsumption":null,"gasProduction":null,"gasConsumption":null},"energyPerGdp":1.426},{"year":2022,"generation":7.75,"demand":9.83,"demandPerCapita":2903,"carbonIntensity":814.2,"netImports":2.08,"netImportsShare":21.16,"population":3386015,"coal":6.65,"gas":0,"oil":0.34,"nuclear":0,"hydro":0.06,"wind":0.51,"solar":0.19,"biofuel":0,"otherRenewables":0,"shares":{"coal":85.81,"gas":0,"oil":4.39,"nuclear":0,"hydro":0.77,"wind":6.58,"solar":2.45,"biofuel":0,"otherRenewables":0,"lowCarbon":9.81,"renewables":9.81,"fossil":90.19},"selfSufficiency":3.974,"fuelTrade":{"coalProduction":208.2,"coalConsumption":null,"oilProduction":null,"oilConsumption":null,"gasProduction":null,"gasConsumption":null},"energyPerGdp":1.169},{"year":2023,"generation":8.29,"demand":10.68,"demandPerCapita":3112,"carbonIntensity":816.6,"netImports":2.39,"netImportsShare":22.38,"population":3431938,"coal":7.06,"gas":0,"oil":0.47,"nuclear":0,"hydro":0.06,"wind":0.51,"solar":0.19,"biofuel":0,"otherRenewables":0,"shares":{"coal":85.16,"gas":0,"oil":5.67,"nuclear":0,"hydro":0.72,"wind":6.15,"solar":2.29,"biofuel":0,"otherRenewables":0,"lowCarbon":9.17,"renewables":9.17,"fossil":90.83},"selfSufficiency":5,"fuelTrade":{"coalProduction":440.4,"coalConsumption":null,"oilProduction":null,"oilConsumption":null,"gasProduction":null,"gasConsumption":null},"energyPerGdp":null},{"year":2024,"generation":8.82,"demand":11.54,"demandPerCapita":3320,"carbonIntensity":810.7,"netImports":2.72,"netImportsShare":23.57,"population":3475541,"coal":7.47,"gas":0,"oil":0.57,"nuclear":0,"hydro":0.06,"wind":0.51,"solar":0.21,"biofuel":0,"otherRenewables":0,"shares":{"coal":84.69,"gas":0,"oil":6.46,"nuclear":0,"hydro":0.68,"wind":5.78,"solar":2.38,"biofuel":0,"otherRenewables":0,"lowCarbon":8.84,"renewables":8.84,"fossil":91.16},"selfSufficiency":null,"fuelTrade":{"coalProduction":563.8,"coalConsumption":null,"oilProduction":null,"oilConsumption":null,"gasProduction":null,"gasConsumption":null},"energyPerGdp":null,"splitEstimated":true},{"year":2025,"generation":9.69,"demand":12.41,"demandPerCapita":3528,"carbonIntensity":816.3,"netImports":2.72,"netImportsShare":21.92,"population":3517097,"coal":8.31,"gas":0,"oil":0.57,"nuclear":0,"hydro":0.06,"wind":0.54,"solar":0.21,"biofuel":0,"otherRenewables":0,"shares":{"coal":85.76,"gas":0,"oil":5.88,"nuclear":0,"hydro":0.62,"wind":5.57,"solar":2.17,"biofuel":0,"otherRenewables":0,"lowCarbon":8.36,"renewables":8.36,"fossil":91.64},"selfSufficiency":null,"fuelTrade":{"coalProduction":null,"coalConsumption":null,"oilProduction":null,"oilConsumption":null,"gasProduction":null,"gasConsumption":null},"energyPerGdp":null,"splitEstimated":true}]}