{"iso3":"SPM","iso2":"PM","name":"Saint Pierre and Miquelon","series":[{"year":2000,"generation":0.04,"demand":0.04,"demandPerCapita":6332,"carbonIntensity":750,"netImports":0,"netImportsShare":0,"population":6317,"coal":0,"gas":0,"oil":0.04,"nuclear":0,"hydro":0,"wind":0,"solar":0,"biofuel":0,"otherRenewables":0,"shares":{"coal":0,"gas":0,"oil":100,"nuclear":0,"hydro":0,"wind":0,"solar":0,"biofuel":0,"otherRenewables":0,"lowCarbon":0,"renewables":0,"fossil":100},"selfSufficiency":0,"fuelTrade":{"coalProduction":0,"coalConsumption":null,"oilProduction":0,"oilConsumption":null,"gasProduction":0,"gasConsumption":null},"energyPerGdp":null},{"year":2001,"generation":0.04,"demand":0.04,"demandPerCapita":6350,"carbonIntensity":750,"netImports":0,"netImportsShare":0,"population":6299,"coal":0,"gas":0,"oil":0.04,"nuclear":0,"hydro":0,"wind":0,"solar":0,"biofuel":0,"otherRenewables":0,"shares":{"coal":0,"gas":0,"oil":100,"nuclear":0,"hydro":0,"wind":0,"solar":0,"biofuel":0,"otherRenewables":0,"lowCarbon":0,"renewables":0,"fossil":100},"selfSufficiency":0,"fuelTrade":{"coalProduction":0,"coalConsumption":null,"oilProduction":0,"oilConsumption":null,"gasProduction":0,"gasConsumption":null},"energyPerGdp":null},{"year":2002,"generation":0.04,"demand":0.04,"demandPerCapita":6377,"carbonIntensity":750,"netImports":0,"netImportsShare":0,"population":6273,"coal":0,"gas":0,"oil":0.04,"nuclear":0,"hydro":0,"wind":0,"solar":0,"biofuel":0,"otherRenewables":0,"shares":{"coal":0,"gas":0,"oil":100,"nuclear":0,"hydro":0,"wind":0,"solar":0,"biofuel":0,"otherRenewables":0,"lowCarbon":0,"renewables":0,"fossil":100},"selfSufficiency":0,"fuelTrade":{"coalProduction":0,"coalConsumption":null,"oilProduction":0,"oilConsumption":null,"gasProduction":0,"gasConsumption":null},"energyPerGdp":null},{"year":2003,"generation":0.04,"demand":0.04,"demandPerCapita":6416,"carbonIntensity":750,"netImports":0,"netImportsShare":0,"population":6234,"coal":0,"gas":0,"oil":0.04,"nuclear":0,"hydro":0,"wind":0,"solar":0,"biofuel":0,"otherRenewables":0,"shares":{"coal":0,"gas":0,"oil":100,"nuclear":0,"hydro":0,"wind":0,"solar":0,"biofuel":0,"otherRenewables":0,"lowCarbon":0,"renewables":0,"fossil":100},"selfSufficiency":0,"fuelTrade":{"coalProduction":0,"coalConsumption":null,"oilProduction":0,"oilConsumption":null,"gasProduction":0,"gasConsumption":null},"energyPerGdp":null},{"year":2004,"generation":0.04,"demand":0.04,"demandPerCapita":6461,"carbonIntensity":750,"netImports":0,"netImportsShare":0,"population":6191,"coal":0,"gas":0,"oil":0.04,"nuclear":0,"hydro":0,"wind":0,"solar":0,"biofuel":0,"otherRenewables":0,"shares":{"coal":0,"gas":0,"oil":100,"nuclear":0,"hydro":0,"wind":0,"solar":0,"biofuel":0,"otherRenewables":0,"lowCarbon":0,"renewables":0,"fossil":100},"selfSufficiency":0,"fuelTrade":{"coalProduction":0,"coalConsumption":null,"oilProduction":0,"oilConsumption":null,"gasProduction":0,"gasConsumption":null},"energyPerGdp":null},{"year":2005,"generation":0.04,"demand":0.04,"demandPerCapita":6516,"carbonIntensity":750,"netImports":0,"netImportsShare":0,"population":6139,"coal":0,"gas":0,"oil":0.04,"nuclear":0,"hydro":0,"wind":0,"solar":0,"biofuel":0,"otherRenewables":0,"shares":{"coal":0,"gas":0,"oil":100,"nuclear":0,"hydro":0,"wind":0,"solar":0,"biofuel":0,"otherRenewables":0,"lowCarbon":0,"renewables":0,"fossil":100},"selfSufficiency":0,"fuelTrade":{"coalProduction":0,"coalConsumption":null,"oilProduction":0,"oilConsumption":null,"gasProduction":0,"gasConsumption":null},"energyPerGdp":null},{"year":2006,"generation":0.04,"demand":0.04,"demandPerCapita":6564,"carbonIntensity":750,"netImports":0,"netImportsShare":0,"population":6094,"coal":0,"gas":0,"oil":0.04,"nuclear":0,"hydro":0,"wind":0,"solar":0,"biofuel":0,"otherRenewables":0,"shares":{"coal":0,"gas":0,"oil":100,"nuclear":0,"hydro":0,"wind":0,"solar":0,"biofuel":0,"otherRenewables":0,"lowCarbon":0,"renewables":0,"fossil":100},"selfSufficiency":0,"fuelTrade":{"coalProduction":0,"coalConsumption":null,"oilProduction":0,"oilConsumption":null,"gasProduction":0,"gasConsumption":null},"energyPerGdp":null},{"year":2007,"generation":0.04,"demand":0.04,"demandPerCapita":6585,"carbonIntensity":750,"netImports":0,"netImportsShare":0,"population":6074,"coal":0,"gas":0,"oil":0.04,"nuclear":0,"hydro":0,"wind":0,"solar":0,"biofuel":0,"otherRenewables":0,"shares":{"coal":0,"gas":0,"oil":100,"nuclear":0,"hydro":0,"wind":0,"solar":0,"biofuel":0,"otherRenewables":0,"lowCarbon":0,"renewables":0,"fossil":100},"selfSufficiency":0,"fuelTrade":{"coalProduction":0,"coalConsumption":null,"oilProduction":0,"oilConsumption":null,"gasProduction":0,"gasConsumption":null},"energyPerGdp":null},{"year":2008,"generation":0.04,"demand":0.04,"demandPerCapita":6597,"carbonIntensity":750,"netImports":0,"netImportsShare":0,"population":6063,"coal":0,"gas":0,"oil":0.04,"nuclear":0,"hydro":0,"wind":0,"solar":0,"biofuel":0,"otherRenewables":0,"shares":{"coal":0,"gas":0,"oil":100,"nuclear":0,"hydro":0,"wind":0,"solar":0,"biofuel":0,"otherRenewables":0,"lowCarbon":0,"renewables":0,"fossil":100},"selfSufficiency":0,"fuelTrade":{"coalProduction":0,"coalConsumption":null,"oilProduction":0,"oilConsumption":null,"gasProduction":0,"gasConsumption":null},"energyPerGdp":null},{"year":2009,"generation":0.04,"demand":0.04,"demandPerCapita":6607,"carbonIntensity":750,"netImports":0,"netImportsShare":0,"population":6054,"coal":0,"gas":0,"oil":0.04,"nuclear":0,"hydro":0,"wind":0,"solar":0,"biofuel":0,"otherRenewables":0,"shares":{"coal":0,"gas":0,"oil":100,"nuclear":0,"hydro":0,"wind":0,"solar":0,"biofuel":0,"otherRenewables":0,"lowCarbon":0,"renewables":0,"fossil":100},"selfSufficiency":0,"fuelTrade":{"coalProduction":0,"coalConsumption":null,"oilProduction":0,"oilConsumption":null,"gasProduction":0,"gasConsumption":null},"energyPerGdp":null},{"year":2010,"generation":0.04,"demand":0.04,"demandPerCapita":6615,"carbonIntensity":750,"netImports":0,"netImportsShare":0,"population":6047,"coal":0,"gas":0,"oil":0.04,"nuclear":0,"hydro":0,"wind":0,"solar":0,"biofuel":0,"otherRenewables":0,"shares":{"coal":0,"gas":0,"oil":100,"nuclear":0,"hydro":0,"wind":0,"solar":0,"biofuel":0,"otherRenewables":0,"lowCarbon":0,"renewables":0,"fossil":100},"selfSufficiency":0,"fuelTrade":{"coalProduction":0,"coalConsumption":null,"oilProduction":0,"oilConsumption":null,"gasProduction":0,"gasConsumption":null},"energyPerGdp":null},{"year":2011,"generation":0.04,"demand":0.04,"demandPerCapita":6627,"carbonIntensity":750,"netImports":0,"netImportsShare":0,"population":6036,"coal":0,"gas":0,"oil":0.04,"nuclear":0,"hydro":0,"wind":0,"solar":0,"biofuel":0,"otherRenewables":0,"shares":{"coal":0,"gas":0,"oil":100,"nuclear":0,"hydro":0,"wind":0,"solar":0,"biofuel":0,"otherRenewables":0,"lowCarbon":0,"renewables":0,"fossil":100},"selfSufficiency":0,"fuelTrade":{"coalProduction":0,"coalConsumption":null,"oilProduction":0,"oilConsumption":null,"gasProduction":0,"gasConsumption":null},"energyPerGdp":null},{"year":2012,"generation":0.04,"demand":0.04,"demandPerCapita":6646,"carbonIntensity":750,"netImports":0,"netImportsShare":0,"population":6019,"coal":0,"gas":0,"oil":0.04,"nuclear":0,"hydro":0,"wind":0,"solar":0,"biofuel":0,"otherRenewables":0,"shares":{"coal":0,"gas":0,"oil":100,"nuclear":0,"hydro":0,"wind":0,"solar":0,"biofuel":0,"otherRenewables":0,"lowCarbon":0,"renewables":0,"fossil":100},"selfSufficiency":0,"fuelTrade":{"coalProduction":0,"coalConsumption":null,"oilProduction":0,"oilConsumption":null,"gasProduction":0,"gasConsumption":null},"energyPerGdp":null},{"year":2013,"generation":0.05,"demand":0.05,"demandPerCapita":8335,"carbonIntensity":600,"netImports":0,"netImportsShare":0,"population":5999,"coal":0,"gas":0,"oil":0.05,"nuclear":0,"hydro":0,"wind":0,"solar":0,"biofuel":0,"otherRenewables":0,"shares":{"coal":0,"gas":0,"oil":100,"nuclear":0,"hydro":0,"wind":0,"solar":0,"biofuel":0,"otherRenewables":0,"lowCarbon":0,"renewables":0,"fossil":100},"selfSufficiency":0,"fuelTrade":{"coalProduction":0,"coalConsumption":null,"oilProduction":0,"oilConsumption":null,"gasProduction":0,"gasConsumption":null},"energyPerGdp":null},{"year":2014,"generation":0.05,"demand":0.05,"demandPerCapita":8356,"carbonIntensity":600,"netImports":0,"netImportsShare":0,"population":5984,"coal":0,"gas":0,"oil":0.05,"nuclear":0,"hydro":0,"wind":0,"solar":0,"biofuel":0,"otherRenewables":0,"shares":{"coal":0,"gas":0,"oil":100,"nuclear":0,"hydro":0,"wind":0,"solar":0,"biofuel":0,"otherRenewables":0,"lowCarbon":0,"renewables":0,"fossil":100},"selfSufficiency":0,"fuelTrade":{"coalProduction":0,"coalConsumption":null,"oilProduction":0,"oilConsumption":null,"gasProduction":0,"gasConsumption":null},"energyPerGdp":null},{"year":2015,"generation":0.05,"demand":0.05,"demandPerCapita":8374,"carbonIntensity":600,"netImports":0,"netImportsShare":0,"population":5971,"coal":0,"gas":0,"oil":0.05,"nuclear":0,"hydro":0,"wind":0,"solar":0,"biofuel":0,"otherRenewables":0,"shares":{"coal":0,"gas":0,"oil":100,"nuclear":0,"hydro":0,"wind":0,"solar":0,"biofuel":0,"otherRenewables":0,"lowCarbon":0,"renewables":0,"fossil":100},"selfSufficiency":0,"fuelTrade":{"coalProduction":0,"coalConsumption":null,"oilProduction":0,"oilConsumption":null,"gasProduction":0,"gasConsumption":null},"energyPerGdp":null,"splitEstimated":true},{"year":2016,"generation":0.05,"demand":0.05,"demandPerCapita":8393,"carbonIntensity":600,"netImports":0,"netImportsShare":0,"population":5957,"coal":0,"gas":0,"oil":0.05,"nuclear":0,"hydro":0,"wind":0,"solar":0,"biofuel":0,"otherRenewables":0,"shares":{"coal":0,"gas":0,"oil":100,"nuclear":0,"hydro":0,"wind":0,"solar":0,"biofuel":0,"otherRenewables":0,"lowCarbon":0,"renewables":0,"fossil":100},"selfSufficiency":0,"fuelTrade":{"coalProduction":0,"coalConsumption":null,"oilProduction":0,"oilConsumption":null,"gasProduction":0,"gasConsumption":null},"energyPerGdp":null,"splitEstimated":true},{"year":2017,"generation":0.05,"demand":0.05,"demandPerCapita":8409,"carbonIntensity":600,"netImports":0,"netImportsShare":0,"population":5946,"coal":0,"gas":0,"oil":0.05,"nuclear":0,"hydro":0,"wind":0,"solar":0,"biofuel":0,"otherRenewables":0,"shares":{"coal":0,"gas":0,"oil":100,"nuclear":0,"hydro":0,"wind":0,"solar":0,"biofuel":0,"otherRenewables":0,"lowCarbon":0,"renewables":0,"fossil":100},"selfSufficiency":0,"fuelTrade":{"coalProduction":null,"coalConsumption":null,"oilProduction":null,"oilConsumption":null,"gasProduction":null,"gasConsumption":null},"energyPerGdp":null,"splitEstimated":true},{"year":2018,"generation":0.05,"demand":0.05,"demandPerCapita":8429,"carbonIntensity":600,"netImports":0,"netImportsShare":0,"population":5932,"coal":0,"gas":0,"oil":0.05,"nuclear":0,"hydro":0,"wind":0,"solar":0,"biofuel":0,"otherRenewables":0,"shares":{"coal":0,"gas":0,"oil":100,"nuclear":0,"hydro":0,"wind":0,"solar":0,"biofuel":0,"otherRenewables":0,"lowCarbon":0,"renewables":0,"fossil":100},"selfSufficiency":0,"fuelTrade":{"coalProduction":null,"coalConsumption":null,"oilProduction":null,"oilConsumption":null,"gasProduction":null,"gasConsumption":null},"energyPerGdp":null,"splitEstimated":true},{"year":2019,"generation":0.05,"demand":0.05,"demandPerCapita":8476,"carbonIntensity":600,"netImports":0,"netImportsShare":0,"population":5899,"coal":0,"gas":0,"oil":0.05,"nuclear":0,"hydro":0,"wind":0,"solar":0,"biofuel":0,"otherRenewables":0,"shares":{"coal":0,"gas":0,"oil":100,"nuclear":0,"hydro":0,"wind":0,"solar":0,"biofuel":0,"otherRenewables":0,"lowCarbon":0,"renewables":0,"fossil":100},"selfSufficiency":0,"fuelTrade":{"coalProduction":null,"coalConsumption":null,"oilProduction":null,"oilConsumption":null,"gasProduction":null,"gasConsumption":null},"energyPerGdp":null,"splitEstimated":true},{"year":2020,"generation":0.05,"demand":0.05,"demandPerCapita":8544,"carbonIntensity":600,"netImports":0,"netImportsShare":0,"population":5852,"coal":0,"gas":0,"oil":0.05,"nuclear":0,"hydro":0,"wind":0,"solar":0,"biofuel":0,"otherRenewables":0,"shares":{"coal":0,"gas":0,"oil":100,"nuclear":0,"hydro":0,"wind":0,"solar":0,"biofuel":0,"otherRenewables":0,"lowCarbon":0,"renewables":0,"fossil":100},"selfSufficiency":0,"fuelTrade":{"coalProduction":null,"coalConsumption":null,"oilProduction":null,"oilConsumption":null,"gasProduction":null,"gasConsumption":null},"energyPerGdp":null,"splitEstimated":true},{"year":2021,"generation":0.05,"demand":0.05,"demandPerCapita":8618,"carbonIntensity":600,"netImports":0,"netImportsShare":0,"population":5802,"coal":0,"gas":0,"oil":0.05,"nuclear":0,"hydro":0,"wind":0,"solar":0,"biofuel":0,"otherRenewables":0,"shares":{"coal":0,"gas":0,"oil":100,"nuclear":0,"hydro":0,"wind":0,"solar":0,"biofuel":0,"otherRenewables":0,"lowCarbon":0,"renewables":0,"fossil":100},"selfSufficiency":0,"fuelTrade":{"coalProduction":null,"coalConsumption":null,"oilProduction":null,"oilConsumption":null,"gasProduction":null,"gasConsumption":null},"energyPerGdp":null,"splitEstimated":true},{"year":2022,"generation":0.05,"demand":0.05,"demandPerCapita":8681,"carbonIntensity":600,"netImports":0,"netImportsShare":0,"population":5760,"coal":0,"gas":0,"oil":0.05,"nuclear":0,"hydro":0,"wind":0,"solar":0,"biofuel":0,"otherRenewables":0,"shares":{"coal":0,"gas":0,"oil":100,"nuclear":0,"hydro":0,"wind":0,"solar":0,"biofuel":0,"otherRenewables":0,"lowCarbon":0,"renewables":0,"fossil":100},"selfSufficiency":0,"fuelTrade":{"coalProduction":null,"coalConsumption":null,"oilProduction":null,"oilConsumption":null,"gasProduction":null,"gasConsumption":null},"energyPerGdp":null,"splitEstimated":true},{"year":2023,"generation":0.05,"demand":0.05,"demandPerCapita":8761,"carbonIntensity":600,"netImports":0,"netImportsShare":0,"population":5707,"coal":0,"gas":0,"oil":0.05,"nuclear":0,"hydro":0,"wind":0,"solar":0,"biofuel":0,"otherRenewables":0,"shares":{"coal":0,"gas":0,"oil":100,"nuclear":0,"hydro":0,"wind":0,"solar":0,"biofuel":0,"otherRenewables":0,"lowCarbon":0,"renewables":0,"fossil":100},"selfSufficiency":0,"fuelTrade":{"coalProduction":null,"coalConsumption":null,"oilProduction":null,"oilConsumption":null,"gasProduction":null,"gasConsumption":null},"energyPerGdp":null,"splitEstimated":true}]}