{"iso3":"ESP","count":102,"byFuel":{"nuclear":5,"gas":31,"hydro":35,"coal":14,"oil":9,"solar":8},"byTier":{"2GW+":1,"1-2GW":14,"500MW-1GW":34,"100-500MW":53},"plants":[{"name":"CN ALMARAZ 1","mw":2017,"lat":39.807,"lon":-5.6986,"fuel":"nuclear","tier":"2GW+","year":1984},{"name":"ASCO GR","mw":1991,"lat":41.2008,"lon":0.5679,"fuel":"nuclear","tier":"1-2GW","year":1983},{"name":"BESOS  GRUPO 5","mw":1671,"lat":41.4196,"lon":2.2294,"fuel":"gas","tier":"1-2GW","year":2010},{"name":"ARCOS DE LA FRONTERA GRUPO 1","mw":1585,"lat":36.6721,"lon":-5.8164,"fuel":"gas","tier":"1-2GW","year":2005},{"name":"CARTAGENA GRUPO 1","mw":1249,"lat":37.5732,"lon":-0.9392,"fuel":"gas","tier":"1-2GW","year":2006},{"name":"CCC SAGUNTO  GRUPO 2","mw":1232,"lat":39.6426,"lon":-0.2344,"fuel":"gas","tier":"1-2GW","year":2007},{"name":"ALDEADAVILA II 2","mw":1226,"lat":41.2117,"lon":-6.6856,"fuel":"hydro","tier":"1-2GW","year":1986},{"name":"ESCOMBRERAS GRUPO 1","mw":1199,"lat":7.5732,"lon":-0.9392,"fuel":"gas","tier":"1-2GW","year":2006},{"name":"PALOS DE LA FRONTERA GRUPO 1","mw":1167,"lat":37.1843,"lon":-6.8857,"fuel":"gas","tier":"1-2GW","year":2004},{"name":"LITORAL DE ALMERIA GR 2","mw":1120,"lat":36.9783,"lon":-1.9054,"fuel":"coal","tier":"1-2GW","year":1997},{"name":"CN COFRENTES","mw":1064,"lat":39.2134,"lon":-1.0509,"fuel":"nuclear","tier":"1-2GW","year":1985},{"name":"TERUEL GR 3","mw":1056,"lat":40.9966,"lon":-0.3798,"fuel":"coal","tier":"1-2GW","year":1980},{"name":"VANDELLOS GR 2","mw":1045,"lat":40.9511,"lon":0.8662,"fuel":"nuclear","tier":"1-2GW","year":1987},{"name":"COMPOSTILLA II GR 5","mw":1005,"lat":42.6125,"lon":-6.5647,"fuel":"coal","tier":"1-2GW","year":1984},{"name":"TRILLO","mw":1003,"lat":40.7016,"lon":-2.6227,"fuel":"nuclear","tier":"1-2GW","year":1988},{"name":"JOSE M ORIOL  GRUPO 4","mw":953,"lat":39.2438,"lon":-0.9317,"fuel":"hydro","tier":"500MW-1GW","year":1970},{"name":"CT SANTURCE 2","mw":897,"lat":43.34,"lon":-3.0539,"fuel":"oil","tier":"500MW-1GW","year":1972},{"name":"ABONO 2","mw":878,"lat":43.5528,"lon":-5.7231,"fuel":"coal","tier":"500MW-1GW","year":1985},{"name":"La Muela II Grupo 4","mw":878,"lat":39.2438,"lon":-0.9317,"fuel":"hydro","tier":"500MW-1GW","year":null},{"name":"PUERTO DE BARCELONA  GRUPO 2","mw":866,"lat":41.3366,"lon":2.1594,"fuel":"gas","tier":"500MW-1GW","year":2010},{"name":"CTCC AS PONTES  GRUPO 5","mw":856,"lat":43.4451,"lon":-7.8621,"fuel":"gas","tier":"500MW-1GW","year":2008},{"name":"CTCC SOTO DE RIBERA  GRUPO 5","mw":854,"lat":43.3161,"lon":-5.8777,"fuel":"gas","tier":"500MW-1GW","year":2011},{"name":"VILLARINO 4","mw":851,"lat":41.2669,"lon":-6.3078,"fuel":"hydro","tier":"500MW-1GW","year":1970},{"name":"CTCC CASTELLON  GRUPO 4","mw":839,"lat":39.9592,"lon":-0.001,"fuel":"gas","tier":"500MW-1GW","year":2008},{"name":"CCC BAHIA DE ALGECIRAS","mw":821,"lat":36.1829,"lon":-5.3905,"fuel":"gas","tier":"500MW-1GW","year":2009},{"name":"CTCC PLANA DEL VENT 2","mw":819,"lat":40.9596,"lon":0.8692,"fuel":"gas","tier":"500MW-1GW","year":2007},{"name":"CTCC ESCOMBRERAS","mw":816,"lat":37.5732,"lon":-0.9392,"fuel":"gas","tier":"500MW-1GW","year":2006},{"name":"ESCATRON","mw":804,"lat":41.2977,"lon":-0.3376,"fuel":"gas","tier":"500MW-1GW","year":2008},{"name":"TARRAGONA","mw":803,"lat":41.1081,"lon":1.1912,"fuel":"gas","tier":"500MW-1GW","year":2004},{"name":"CASTEJON  GRUPO 2","mw":797,"lat":42.1718,"lon":-1.6773,"fuel":"gas","tier":"500MW-1GW","year":2007},{"name":"SAN ROQUE GRUPO 2","mw":792,"lat":36.1955,"lon":-5.4131,"fuel":"gas","tier":"500MW-1GW","year":2002},{"name":"CICLO COMBINADO DE CASTELNOU","mw":791,"lat":41.2167,"lon":-0.2928,"fuel":"gas","tier":"500MW-1GW","year":2006},{"name":"AMOREBIETA","mw":786,"lat":43.2347,"lon":-2.7497,"fuel":"gas","tier":"500MW-1GW","year":2005},{"name":"ARRUBAL GRUPO 1","mw":785,"lat":42.4194,"lon":-2.2511,"fuel":"gas","tier":"500MW-1GW","year":2005},{"name":"CASTELLON","mw":782,"lat":39.9592,"lon":-0.001,"fuel":"gas","tier":"500MW-1GW","year":2002},{"name":"CAMPO DE GIBRALTAR GRUPO 20","mw":781,"lat":36.1834,"lon":-5.3933,"fuel":"gas","tier":"500MW-1GW","year":2004},{"name":"ACECA  GRUPO 4","mw":759,"lat":39.9427,"lon":-3.8548,"fuel":"gas","tier":"500MW-1GW","year":2006},{"name":"BAHIA DE ALGECIRAS I","mw":731,"lat":36.1829,"lon":-5.3905,"fuel":"gas","tier":"500MW-1GW","year":1970},{"name":"GRANADILLA 1  GAS 1","mw":693,"lat":28.0863,"lon":-16.4939,"fuel":"oil","tier":"500MW-1GW","year":1990},{"name":"BARRANCO DE TIRAJANA 7  VAPOR 3 (CC1)","mw":646,"lat":27.8045,"lon":-15.4387,"fuel":"oil","tier":"500MW-1GW","year":2008},{"name":"LA MUELA CORTES 1","mw":634,"lat":39.2628,"lon":-0.9192,"fuel":"hydro","tier":"500MW-1GW","year":1989},{"name":"LA ROBLA GRUPO 2","mw":619,"lat":42.7924,"lon":-5.634,"fuel":"coal","tier":"500MW-1GW","year":1984},{"name":"LOS BARRIOS","mw":570,"lat":36.1828,"lon":-5.42,"fuel":"coal","tier":"500MW-1GW","year":1985},{"name":"SON REUS 3  TURBINA DE GAS N 3","mw":564,"lat":39.65,"lon":2.6807,"fuel":"oil","tier":"500MW-1GW","year":2000},{"name":"MEIRAMA GRUPO 1","mw":557,"lat":43.1685,"lon":-8.4111,"fuel":"coal","tier":"500MW-1GW","year":1980},{"name":"NARCEA GRUPO 3","mw":554,"lat":43.2924,"lon":-6.3937,"fuel":"coal","tier":"500MW-1GW","year":1984},{"name":"CT ESCOMBRERAS 5","mw":537,"lat":37.5645,"lon":-0.9513,"fuel":"oil","tier":"500MW-1GW","year":1968},{"name":"ALCUDIA 1  GRUPO N 1","mw":534,"lat":39.8106,"lon":3.0913,"fuel":"coal","tier":"500MW-1GW","year":1981},{"name":"SAUCELLE II 1","mw":516,"lat":41.045,"lon":-6.8067,"fuel":"hydro","tier":"500MW-1GW","year":1989},{"name":"CEDILLO 3","mw":495,"lat":39.6643,"lon":-7.5332,"fuel":"hydro","tier":"100-500MW","year":1976},{"name":"CT GUARDO 2","mw":486,"lat":42.8261,"lon":-4.8463,"fuel":"coal","tier":"100-500MW","year":1984},{"name":"San Esteban II  Grupo 1","mw":438,"lat":42.4143,"lon":-7.6533,"fuel":"hydro","tier":"100-500MW","year":2012},{"name":"CAS TRESORER TG3  CC2","mw":429,"lat":39.5672,"lon":2.6895,"fuel":"gas","tier":"100-500MW","year":2009},{"name":"CTCC CASTEJON  GRUPO 1","mw":425,"lat":42.1718,"lon":-1.6773,"fuel":"gas","tier":"100-500MW","year":2002},{"name":"MALA1 (CTCC MALAGA)","mw":416,"lat":36.7495,"lon":-4.5631,"fuel":"gas","tier":"100-500MW","year":2009},{"name":"SANTURCE  GRUPO 4","mw":396,"lat":43.34,"lon":-3.0539,"fuel":"gas","tier":"100-500MW","year":2005},{"name":"CRISTOBAL COLON","mw":391,"lat":37.2156,"lon":-6.943,"fuel":"gas","tier":"100-500MW","year":2006},{"name":"CTCC SABON  GRUPO 3","mw":391,"lat":43.329,"lon":-8.503,"fuel":"gas","tier":"100-500MW","year":2008},{"name":"TAJO DE LA ENCANTADA 1","mw":377,"lat":36.9083,"lon":-4.7631,"fuel":"hydro","tier":"100-500MW","year":1977},{"name":"AGUAYO 3","mw":361,"lat":43.0952,"lon":-4.0004,"fuel":"hydro","tier":"100-500MW","year":1983},{"name":"CT LADA 4","mw":348,"lat":43.3082,"lon":-5.7001,"fuel":"coal","tier":"100-500MW","year":1981},{"name":"ANLLARES GR 1","mw":347,"lat":42.8385,"lon":-6.5332,"fuel":"coal","tier":"100-500MW","year":1982},{"name":"SOTO RIBERA 3","mw":346,"lat":43.3122,"lon":-5.8739,"fuel":"coal","tier":"100-500MW","year":1984},{"name":"BELESAR GRUPO 2","mw":331,"lat":42.6263,"lon":-7.7135,"fuel":"hydro","tier":"100-500MW","year":1963},{"name":"RICOBAYO II 1","mw":327,"lat":41.5278,"lon":-5.9877,"fuel":"hydro","tier":"100-500MW","year":1999},{"name":"MEQUINENZA 1","mw":322,"lat":41.3687,"lon":0.2765,"fuel":"hydro","tier":"100-500MW","year":1964},{"name":"PUENTE BIBEY 4","mw":312,"lat":42.3921,"lon":-7.2191,"fuel":"hydro","tier":"100-500MW","year":1966},{"name":"PUENTE NUEVO GR 3","mw":300,"lat":38.1108,"lon":-4.9354,"fuel":"coal","tier":"100-500MW","year":1980},{"name":"CTCC ESCATRON","mw":275,"lat":41.2977,"lon":-0.3376,"fuel":"gas","tier":"100-500MW","year":2007},{"name":"CONSO 2","mw":268,"lat":42.1142,"lon":-7.209,"fuel":"hydro","tier":"100-500MW","year":1975},{"name":"RIBA ROJA 1","mw":261,"lat":41.2422,"lon":0.4309,"fuel":"hydro","tier":"100-500MW","year":1969},{"name":"VALDECANAS 3","mw":247,"lat":39.7778,"lon":-5.6124,"fuel":"hydro","tier":"100-500MW","year":1964},{"name":"JINAMAR 10  GAS 2","mw":234,"lat":28.0424,"lon":-15.4114,"fuel":"oil","tier":"100-500MW","year":1989},{"name":"MORALETS 1","mw":219,"lat":42.5787,"lon":0.7587,"fuel":"hydro","tier":"100-500MW","year":1985},{"name":"VILLALCAMPO II","mw":216,"lat":39.2077,"lon":-1.2401,"fuel":"hydro","tier":"100-500MW","year":1977},{"name":"BOLARQUE II GRUPO 1","mw":215,"lat":40.364,"lon":-2.8289,"fuel":"hydro","tier":"100-500MW","year":1973},{"name":"SOUTELO 2","mw":214,"lat":42.1677,"lon":-7.1744,"fuel":"hydro","tier":"100-500MW","year":1994},{"name":"GUILLENA 1","mw":208,"lat":37.641,"lon":-6.0724,"fuel":"hydro","tier":"100-500MW","year":1973},{"name":"SOLABEN 3","mw":200,"lat":39.226,"lon":-5.3905,"fuel":"solar","tier":"100-500MW","year":2012},{"name":"AZUTAN 2","mw":198,"lat":39.7799,"lon":-5.0876,"fuel":"hydro","tier":"100-500MW","year":1970},{"name":"CASTRO II","mw":195,"lat":41.5756,"lon":-6.1891,"fuel":"hydro","tier":"100-500MW","year":1977},{"name":"MAHON 10  BURMEISTER N 2","mw":195,"lat":39.8964,"lon":4.2597,"fuel":"oil","tier":"100-500MW","year":1991},{"name":"PUNTA GRANDE 19 DIESEL 11","mw":185,"lat":28.963,"lon":-13.5477,"fuel":"oil","tier":"100-500MW","year":2013},{"name":"LOS PEARES GRUPO 2","mw":181,"lat":42.4637,"lon":-7.7237,"fuel":"hydro","tier":"100-500MW","year":1954},{"name":"Don Rodrigo","mw":175,"lat":37.228,"lon":-5.867,"fuel":"solar","tier":"100-500MW","year":null},{"name":"FRIEIRA GRUPO 1","mw":161,"lat":42.1538,"lon":-8.1933,"fuel":"hydro","tier":"100-500MW","year":1970},{"name":"SALIME 4","mw":157,"lat":43.2364,"lon":-6.8475,"fuel":"hydro","tier":"100-500MW","year":1956},{"name":"CANDELARIA 9  VAPOR 5","mw":154,"lat":28.3548,"lon":-16.3727,"fuel":"oil","tier":"100-500MW","year":1979},{"name":"TAVASCAN INFERIOR","mw":151,"lat":42.637,"lon":1.2512,"fuel":"hydro","tier":"100-500MW","year":1971},{"name":"ANDASOL-3","mw":150,"lat":37.2281,"lon":-3.0511,"fuel":"solar","tier":"100-500MW","year":2011},{"name":"EXTRESOL-1","mw":150,"lat":38.64,"lon":-6.744,"fuel":"solar","tier":"100-500MW","year":2009},{"name":"PLANTA SOLAR TERMICA SOLNOVA 1","mw":150,"lat":37.4179,"lon":-6.2771,"fuel":"solar","tier":"100-500MW","year":2010},{"name":"CASTRELO GRUPO 1","mw":136,"lat":42.2917,"lon":-8.1136,"fuel":"hydro","tier":"100-500MW","year":1969},{"name":"CORNATEL GR 1","mw":131,"lat":42.4496,"lon":-6.9476,"fuel":"hydro","tier":"100-500MW","year":1963},{"name":"TORREJON 1","mw":130,"lat":39.5357,"lon":-5.9891,"fuel":"hydro","tier":"100-500MW","year":1967},{"name":"TANES 1","mw":124,"lat":43.2207,"lon":-5.4278,"fuel":"hydro","tier":"100-500MW","year":1978},{"name":"COFRENTES 1","mw":121,"lat":39.2167,"lon":-1.05,"fuel":"hydro","tier":"100-500MW","year":1951},{"name":"GABRIEL Y GALAN","mw":110,"lat":40.2211,"lon":-6.133,"fuel":"hydro","tier":"100-500MW","year":1982},{"name":"CANELLES 1","mw":107,"lat":41.9763,"lon":0.6116,"fuel":"hydro","tier":"100-500MW","year":1959},{"name":"PLANTA SOLAR TERMICA HELIOENERGY 1","mw":100,"lat":37.5729,"lon":-5.1449,"fuel":"solar","tier":"100-500MW","year":2011},{"name":"PST SOLACOR 1","mw":100,"lat":37.9582,"lon":-4.4981,"fuel":"solar","tier":"100-500MW","year":2012},{"name":"Palma del Rio CSP","mw":100,"lat":37.648,"lon":-5.254,"fuel":"solar","tier":"100-500MW","year":null}]}