{"iso3":"SAU","count":98,"source":{"label":"GEM Global Integrated Power Tracker (Mar 2026)","url":"https://globalenergymonitor.org/projects/global-integrated-power-tracker/","year":2026},"byFuel":{"oil":22,"gas":62,"solar":13,"wind":1},"byTier":{"2GW+":19,"1-2GW":22,"500MW-1GW":13,"100-500MW":44},"plants":[{"name":"Rabigh power plant","mw":4480,"lat":22.6702,"lon":39.0585,"fuel":"oil","tier":"2GW+","year":2009},{"name":"Ghazlan power plant","mw":4256,"lat":26.8541,"lon":49.8976,"fuel":"gas","tier":"2GW+","year":1980},{"name":"Qurayyah CC power plant","mw":4098,"lat":25.8446,"lon":50.1264,"fuel":"gas","tier":"2GW+","year":2014},{"name":"Jizan IGCC power plant","mw":3850,"lat":17.2754,"lon":42.368,"fuel":"gas","tier":"2GW+","year":2020},{"name":"Shoaiba power plant","mw":3840,"lat":20.6801,"lon":39.5232,"fuel":"oil","tier":"2GW+","year":2003},{"name":"Qurayyah ll power plant","mw":3774,"lat":25.8255,"lon":50.1337,"fuel":"gas","tier":"2GW+","year":2012},{"name":"Riyadh 9 power plant","mw":3760,"lat":24.9486,"lon":47.0636,"fuel":"gas","tier":"2GW+","year":1997},{"name":"Riyadh 10 power plant","mw":3520,"lat":24.4206,"lon":47.0195,"fuel":"gas","tier":"2GW+","year":2015},{"name":"Yanbu 3 power plant","mw":3135,"lat":23.9745,"lon":38.2148,"fuel":"gas","tier":"2GW+","year":2019},{"name":"MARAFIQ Independent Water and power plant","mw":2744,"lat":26.8966,"lon":49.7769,"fuel":"gas","tier":"2GW+","year":2010},{"name":"Ras Al-Khair power plant","mw":2690,"lat":27.5367,"lon":49.1389,"fuel":"gas","tier":"2GW+","year":2014},{"name":"Jeddah South power plant","mw":2640,"lat":21.2121,"lon":39.1773,"fuel":"oil","tier":"2GW+","year":2016},{"name":"Shuqaiq Steam Power Plant","mw":2640,"lat":16.9129,"lon":42.5788,"fuel":"oil","tier":"2GW+","year":2019},{"name":"Qurayyah Thermal power plant","mw":2500,"lat":25.8592,"lon":50.1178,"fuel":"gas","tier":"2GW+","year":1988},{"name":"Riyadh 12 power plant","mw":2175,"lat":24.7837,"lon":45.6053,"fuel":"gas","tier":"2GW+","year":2015},{"name":"Riyadh 8 power plant","mw":2090,"lat":24.5946,"lon":46.5718,"fuel":"gas","tier":"2GW+","year":1983},{"name":"Rabigh 2 IPP power station","mw":2060,"lat":22.6289,"lon":39.0467,"fuel":"gas","tier":"2GW+","year":2018},{"name":"Shuaibah 2 solar farm","mw":2060,"lat":20.7825,"lon":39.5786,"fuel":"solar","tier":"2GW+","year":2025},{"name":"Ar Rass Solar PV 2","mw":2000,"lat":25.5934,"lon":43.631,"fuel":"solar","tier":"2GW+","year":2025},{"name":"Riyadh City-14 power station","mw":1980,"lat":24.6124,"lon":46.1518,"fuel":"gas","tier":"1-2GW","year":2019},{"name":"Riyadh PP11 power station","mw":1805,"lat":24.7734,"lon":46.6563,"fuel":"gas","tier":"1-2GW","year":1979},{"name":"Riyadh City-13 power station","mw":1800,"lat":24.785,"lon":45.6215,"fuel":"gas","tier":"1-2GW","year":2020},{"name":"Jeddah PP3 power plant","mw":1791,"lat":21.4331,"lon":39.2039,"fuel":"oil","tier":"1-2GW","year":1976},{"name":"Faras power plant","mw":1610,"lat":25.2106,"lon":49.2903,"fuel":"gas","tier":"1-2GW","year":2011},{"name":"Jubail (SWCC) power station","mw":1570,"lat":26.8966,"lon":49.7769,"fuel":"gas","tier":"1-2GW","year":1980},{"name":"Fadhili cogeneration power plant","mw":1520,"lat":27.1123,"lon":49.0714,"fuel":"gas","tier":"1-2GW","year":2020},{"name":"Shaybah Gas power plant","mw":1500,"lat":22.6062,"lon":54.0711,"fuel":"gas","tier":"1-2GW","year":2018},{"name":"Sudair Solar PV Project","mw":1500,"lat":25.7688,"lon":45.5872,"fuel":"solar","tier":"1-2GW","year":2023},{"name":"Al Kahfah solar farm","mw":1425,"lat":26.9848,"lon":42.989,"fuel":"solar","tier":"1-2GW","year":2025},{"name":"Waad Al Shamal power station","mw":1390,"lat":27.5365,"lon":49.1865,"fuel":"gas","tier":"1-2GW","year":2018},{"name":"Riyadh 7 power plant","mw":1316,"lat":24.57,"lon":46.883,"fuel":"gas","tier":"1-2GW","year":1980},{"name":"Rabigh IPP power station","mw":1204,"lat":22.6636,"lon":39.0367,"fuel":"oil","tier":"1-2GW","year":2013},{"name":"Shoaiba II CCPP Project","mw":1200,"lat":20.6299,"lon":39.5625,"fuel":"oil","tier":"1-2GW","year":2014},{"name":"Tehama Central power station","mw":1191,"lat":19.0994,"lon":41.1584,"fuel":"oil","tier":"1-2GW","year":1982},{"name":"Alkhobar power plant","mw":1190,"lat":26.18,"lon":50.209,"fuel":"gas","tier":"1-2GW","year":1982},{"name":"Yanbu 1 power plant","mw":1149,"lat":23.9104,"lon":38.3216,"fuel":"gas","tier":"1-2GW","year":1982},{"name":"Saad Solar PV Plant 2","mw":1125,"lat":25.0604,"lon":47.5497,"fuel":"solar","tier":"1-2GW","year":2025},{"name":"Shedgum power plant","mw":1101,"lat":25.6521,"lon":49.3915,"fuel":"gas","tier":"1-2GW","year":1978},{"name":"Rabigh-2 power plant","mw":1089,"lat":22.6702,"lon":39.0585,"fuel":"oil","tier":"1-2GW","year":1994},{"name":"Al-Qassim power plant","mw":1080,"lat":26.2063,"lon":44.0092,"fuel":"oil","tier":"1-2GW","year":2017},{"name":"Shuqaiq 2 Independent Water and Power Project","mw":1020,"lat":17.6596,"lon":42.0761,"fuel":"oil","tier":"1-2GW","year":2010},{"name":"Tanajib Cogeneration and Desalination power plant","mw":940,"lat":27.7703,"lon":48.8748,"fuel":"gas","tier":"500MW-1GW","year":2025},{"name":"Hail-2 power plant","mw":926,"lat":27.4705,"lon":41.7411,"fuel":"gas","tier":"500MW-1GW","year":1985},{"name":"Jizan Central power plant","mw":867,"lat":16.9386,"lon":42.6341,"fuel":"gas","tier":"500MW-1GW","year":2003},{"name":"Wasit Gas power plant","mw":856,"lat":27.11,"lon":49.312,"fuel":"gas","tier":"500MW-1GW","year":2014},{"name":"Petro-Rabigh Independent Water Steam and Power Project","mw":830,"lat":22.7053,"lon":39.02,"fuel":"oil","tier":"500MW-1GW","year":2008},{"name":"Yanbu 2 power plant","mw":825,"lat":23.9104,"lon":38.3814,"fuel":"gas","tier":"500MW-1GW","year":2012},{"name":"Shuaiba SWCC power plant","mw":810,"lat":20.68,"lon":39.5248,"fuel":"oil","tier":"500MW-1GW","year":1988},{"name":"Makkah 2 power plant","mw":779,"lat":21.4731,"lon":39.7992,"fuel":"oil","tier":"500MW-1GW","year":1975},{"name":"Tabuk PP2 power plant","mw":744,"lat":28.4707,"lon":36.5191,"fuel":"gas","tier":"500MW-1GW","year":2005},{"name":"Ar Rass Solar PV","mw":700,"lat":25.6089,"lon":43.5946,"fuel":"solar","tier":"500MW-1GW","year":2024},{"name":"Riyadh 5 power plant","mw":606,"lat":24.7169,"lon":46.7247,"fuel":"oil","tier":"500MW-1GW","year":1982},{"name":"Al-Faisaliah (Shuaibah) Solar","mw":600,"lat":20.7374,"lon":39.6065,"fuel":"solar","tier":"500MW-1GW","year":2024},{"name":"Green Duba ISCC power plant","mw":550,"lat":27.751,"lon":35.4433,"fuel":"gas","tier":"500MW-1GW","year":2022},{"name":"Juaymah cogeneration Gas power plant","mw":497,"lat":27.0196,"lon":49.5784,"fuel":"gas","tier":"100-500MW","year":2006},{"name":"Shedgum cogeneration Gas power plant","mw":497,"lat":25.6516,"lon":49.3855,"fuel":"gas","tier":"100-500MW","year":2006},{"name":"Uthmaniyah cogeneration Gas power plant","mw":497,"lat":25.19,"lon":49.307,"fuel":"gas","tier":"100-500MW","year":2006},{"name":"Najran power plant","mw":483,"lat":17.5973,"lon":44.3378,"fuel":"oil","tier":"100-500MW","year":1985},{"name":"Tabuk 1 power plant","mw":448,"lat":28.471,"lon":36.5164,"fuel":"oil","tier":"100-500MW","year":2004},{"name":"Asir Central power plant","mw":432,"lat":18.2761,"lon":42.538,"fuel":"gas","tier":"100-500MW","year":2003},{"name":"Manifa cogeneration power plant","mw":420,"lat":27.5874,"lon":48.9728,"fuel":"gas","tier":"100-500MW","year":2014},{"name":"Rabigh Solar PV","mw":400,"lat":22.5808,"lon":39.1683,"fuel":"solar","tier":"100-500MW","year":2023},{"name":"Red Sea Solar Plant","mw":400,"lat":25.4296,"lon":37.1128,"fuel":"solar","tier":"100-500MW","year":2024},{"name":"Dumat Al Jandal wind farm","mw":400,"lat":29.9543,"lon":39.9037,"fuel":"wind","tier":"100-500MW","year":2021},{"name":"Al Dammam power plant","mw":398,"lat":26.38,"lon":50.093,"fuel":"gas","tier":"100-500MW","year":null},{"name":"Khursaniyah power plant","mw":370,"lat":27.15,"lon":49.207,"fuel":"gas","tier":"100-500MW","year":2008},{"name":"Bisha Central power plant","mw":363,"lat":19.9863,"lon":42.3938,"fuel":"gas","tier":"100-500MW","year":1984},{"name":"Abqaiq cogeneration power station","mw":360,"lat":25.9311,"lon":49.6844,"fuel":"gas","tier":"100-500MW","year":2017},{"name":"Ras Tanura cogeneration power station","mw":356,"lat":26.6936,"lon":50.1033,"fuel":"gas","tier":"100-500MW","year":2017},{"name":"Al-Jouf power plant","mw":348,"lat":29.7755,"lon":40.01,"fuel":"gas","tier":"100-500MW","year":2008},{"name":"Jafurah Cogeneration power plant","mw":320,"lat":24.5079,"lon":45.8855,"fuel":"gas","tier":"100-500MW","year":2025},{"name":"Jeddah Solar Project","mw":300,"lat":21.1522,"lon":39.411,"fuel":"solar","tier":"100-500MW","year":2023},{"name":"Sakaka Solar","mw":300,"lat":29.727,"lon":40.0974,"fuel":"solar","tier":"100-500MW","year":2020},{"name":"Berri Gas power plant","mw":298,"lat":26.96,"lon":49.595,"fuel":"gas","tier":"100-500MW","year":2005},{"name":"Al Qurayyat power plant","mw":294,"lat":31.2542,"lon":37.4302,"fuel":"gas","tier":"100-500MW","year":2012},{"name":"Rafha power plant","mw":286,"lat":29.4841,"lon":43.5401,"fuel":"gas","tier":"100-500MW","year":2012},{"name":"Arar power plant","mw":274,"lat":30.928,"lon":41.0593,"fuel":"gas","tier":"100-500MW","year":2006},{"name":"Madinah PP2 power plant","mw":270,"lat":21.4731,"lon":39.7992,"fuel":"oil","tier":"100-500MW","year":1998},{"name":"Uthmaniyah power station","mw":256,"lat":25.19,"lon":49.312,"fuel":"gas","tier":"100-500MW","year":1974},{"name":"Jubail cogeneration power plant","mw":250,"lat":27.0257,"lon":49.5201,"fuel":"gas","tier":"100-500MW","year":2005},{"name":"Amaala solar farm","mw":250,"lat":26.6421,"lon":36.2273,"fuel":"solar","tier":"100-500MW","year":2025},{"name":"Juba power plant","mw":234,"lat":20.2317,"lon":44.9115,"fuel":"gas","tier":"100-500MW","year":2009},{"name":"Saudi Cement power plant","mw":221,"lat":25.7392,"lon":49.5676,"fuel":"oil","tier":"100-500MW","year":null},{"name":"Sharurah power plant","mw":213,"lat":17.4793,"lon":47.1088,"fuel":"gas","tier":"100-500MW","year":2010},{"name":"Al Wajh power station","mw":180,"lat":26.2235,"lon":36.4931,"fuel":"gas","tier":"100-500MW","year":2013},{"name":"Altaaqa 3 Mobile power plant","mw":180,"lat":24.6822,"lon":45.0302,"fuel":"gas","tier":"100-500MW","year":2018},{"name":"Yamama power plant","mw":161,"lat":24.7023,"lon":47.5312,"fuel":"gas","tier":"100-500MW","year":2019},{"name":"Hawiyah cogeneration power station","mw":160,"lat":24.8038,"lon":49.3526,"fuel":"gas","tier":"100-500MW","year":2016},{"name":"Karan Gas power plant","mw":150,"lat":27.15,"lon":49.207,"fuel":"gas","tier":"100-500MW","year":2012},{"name":"Ras Tanura Tihama power station","mw":150,"lat":26.8003,"lon":50.0039,"fuel":"gas","tier":"100-500MW","year":2006},{"name":"Yanbu 2 SWCC power plant","mw":150,"lat":23.8655,"lon":38.3798,"fuel":"gas","tier":"100-500MW","year":2000},{"name":"Qatif G-1 power plant","mw":144,"lat":26.55,"lon":49.932,"fuel":"gas","tier":"100-500MW","year":2004},{"name":"Altaaqa 4 Mobile power plant","mw":125,"lat":19.4332,"lon":48.5927,"fuel":"oil","tier":"100-500MW","year":2023},{"name":"Juaymah power plant","mw":121,"lat":26.8,"lon":50.006,"fuel":"gas","tier":"100-500MW","year":1976},{"name":"Wadi Ad Dawasir Solar PV Plant","mw":119,"lat":20.5595,"lon":44.8657,"fuel":"solar","tier":"100-500MW","year":2025},{"name":"Altaaqa 2 Mobile power plant","mw":110,"lat":24.6822,"lon":45.0302,"fuel":"oil","tier":"100-500MW","year":2017},{"name":"Hofuf (KSA) Captive power plant","mw":108,"lat":25.6843,"lon":49.5135,"fuel":"gas","tier":"100-500MW","year":2008},{"name":"Tabarjal power plant","mw":103,"lat":30.4705,"lon":38.2295,"fuel":"oil","tier":"100-500MW","year":2002}]}